{"Deutsch":"von A bis Z; detailliert; in allen Einzelheiten ","English":"lit. count by fives and tens (idiom); to narrate systematically and in full detail","francais":"raconter en détail ou tout au long","h":[{"=":"583700239","b":"ㄧ　ㄨˇ　ㄧ　ㄕˊ","d":[{"f":"`數數~`目~`時~`普通~`以~`五~`為~`單位~，`故以~`一~`五~、`一~`十~`指~`計~`數~`的~`動作~。","q":["《`儒林外史~．`第~`五~○`回~》：「`等~`他~`官司~`贏~`了~`來~，`得了~`缺~，`叫~`他~`一五一十~`算了~`來~`還~`你~。」","《`紅樓夢~．`第~`二~`六~`回~》：「`便~`把~`手帕子~`打開~，`把錢~`倒~`了~`出來~，`紅玉~`替~`他~`一五一十~`的~`數~`了收~`起~。」"]},{"f":"`比喻~`把~`事情~`從頭至尾~`詳細~`說~`出~，`無~`所~`遺漏~。","q":["《`初~`刻~`拍案驚奇~．`卷~`二~》：「`那~`男女~`見~`不是~`勢頭~，`盒~`盤~`也~`不出~，`仍舊~`挑~`了~，`走~`了~`回家~，`一五一十~`的~`對~`家主~`說~`了~。」"]}],"p":"yī wǔ yī shí"}],"t":"`一~`五~`一~`十~","translation":{"Deutsch":["von A bis Z; detailliert; in allen Einzelheiten "],"English":["lit. count by fives and tens (idiom); to narrate systematically and in full detail"],"francais":["raconter en détail ou tout au long"]}}