{"h":[{"b":"ㄧ　ㄉㄠ　ㄌㄧㄤˇ　ㄉㄨㄢˋ","d":[{"f":"`一刀切~`成~`兩~`段~。`意指~`將~`人~`殺死~。`元~．`關漢卿~《`蝴蝶夢~．`第~`三~`折~》：「`到~`來日~`一刀兩段~，`橫~`屍~`在~`市廛~。」《`東歐~`女~`豪傑~．`第~`四~`回~》：「`到~`了~`那個~`時候~，`趁~`著~`勢頭~，`先~`把~`禁子~`一刀兩段~，`然後~`打開~`監門~，`便~`帶~`了~`蘇~`姑娘~`出來~。」`也~`作~「`一刀兩斷~」。"},{"f":"`比喻~`斷絕~`關係~。《`三國演義~．`第~`四七~`回~》：「`今日~`無故~`又~`來~，`必~`不懷好意~！`吾~`不~`看~`舊日~`之~`情~，`一刀兩段~！」《`孽~`海~`花~．`第~`三~○`回~》：「`不要~`三~`兒~`有了~`別~`的~`花樣~`罷~？`要是~`這樣~，`還是~`趁早~`和~`他~`一刀兩段~`的~`好~，`省得~`牽腸掛肚~`不爽快~。」`也~`作~「`一刀兩斷~」。"},{"f":"`形容~`乾脆爽快~`的~`作法~。《`警世通言~．`卷~`一一~．`蘇~`知縣~`羅~`衫~`再~`合~》：「`我~`是~`一刀兩段~`的~`性子~，`不~`學~`那~`粘皮帶骨~。」`也~`作~「`一刀兩斷~」。"}],"p":"yī dāo liǎng duàn"}],"t":"`一刀~`兩~`段~"}