{"English":"feelings of the masses","h":[{"=":"390700049","b":"ㄒㄧㄚˋ　ㄑㄧㄥˊ","d":[{"f":"`民情~。","q":["《`管子~．`明法~》：「`夫~`國有~`四~`亡~，`令~`求~`不出~`謂~`之~`滅~，`出~`而~`道~`留~`謂~`之~`擁~，`下情~`求~`不上~`通~`謂~`之~`塞~，`下情~`上~`而~`道~`止~`謂~`之~`侵~。」","《`漢書~．`卷~`八~．`宣~`帝~`紀~》：「`而~`令~`群~`臣~`得~`奏~`封事~，`以~`知~`下情~。」"]},{"f":"`對~`尊者~`表白~`時~，`稱~`自己~`的~`情況~`或~`心情~`的~`謙辭~。","q":["《`文選~．`任昉~．`為~`蕭~`揚州~`薦~`士~`表~》：「`臨~`表~`悚~`戰~，`猶~`懼~`未~`允~，`不任~`下情~`云云~。」","《`南齊書~．`卷~`二~`二~．`豫章~`文獻~`王~`傳~》：「`而~`臣~`頓~`有~　`二~`處~`住~`止~，`下情~`所~`竊~`未~`安~。」"]}],"p":"xià qíng"}],"t":"`下~`情~","translation":{"English":["feelings of the masses","my situation (humble speech)"]}}