{"Deutsch":"Milch ","English":"breast","c":8,"francais":"lait","h":[{"=":"5237","b":"ㄖㄨˇ","d":[{"e":["`如~：「`孳乳~」。"],"f":"`生產~、`繁殖~。","q":["《`史記~．`卷~`一~○`五~．`扁鵲~`倉公~`傳~》：「`菑~`川~`王~`美人~`懷子~`而~`不~`乳~，`來~`召~`臣~`意~。」","《`漢書~．`卷~`五~`四~．`蘇~`建~`傳~》：「`乃~`徙~`武~`北海~`上~`無~`人~`處~，`使~`牧~`羝~，`羝~`乳~`乃~`得~`歸~。」"],"type":"`動~"},{"f":"`孵~`卵~、`孵化~。","q":["《`禮記~．`月令~》：「`雉雊~`雞~`乳~。」","《`魏書~．`卷~`一~○`七~．`律曆志~`上~》：「`立春~， `雞~`始~`乳~。」"],"type":"`動~"},{"f":"`哺育~、`餵~`奶~。","q":["《`左傳~．`宣~`公~`四~`年~》：「䢵`夫人~`使~`棄~`諸~`夢~`中~，`虎~`乳~`之~。」","《`新唐書~．`卷~`一~`九~`四~．`元~`德~`秀~`傳~》：「`德~`秀~`自~`乳~`之~。」"],"type":"`動~"},{"f":"`飲~、`喝~。","q":["《`文選~．`鮑照~．`蕪~`城~`賦~》：「`伏~`虣~`藏~`虎~，`乳~`血~`飧~`膚~。」"],"type":"`動~"},{"f":"`乳房~`的~`簡稱~。","q":["《`史記~．`卷~`一~○`五~．`扁鵲~`倉公~`傳~》：「`意~`告~`之後~`百~`餘~`日~，`果~`為~`疽~`發~`乳~`上~，`入~`缺~`盆~，`死~。」"],"type":"`名~"},{"e":["`如~：「`母~`乳~」、「`牛乳~」、「`鮮乳~」。"],"f":"`奶~`汁~。","type":"`名~"},{"f":"`像~`乳房~`的~`物體~。","q":["`明~．`徐~`弘~`祖~《`徐霞客遊記~．`卷~`三~`下~．`粵~`西~`遊~`日記~`二~》：「`岐~`中~`倒~`垂~`一~`乳~，`長~`數~`丈~，`其~`端~`空~`懸~，`水~`由~`端~`涓涓~`下~。」"],"type":"`名~"},{"e":["`如~：「`豆乳~」、「`蜂王乳~」。"],"f":"`類似~`乳汁~`的~`液體~。","type":"`名~"},{"e":["`如~：「`乳燕~」、「`乳豬~」、「`乳~`鴿~」。"],"f":"`初~`生~`的~。","type":"`形~"}],"p":"rǔ"}],"n":7,"r":"`乙~","t":"乳","translation":{"Deutsch":["Milch "],"English":["breast","milk"],"francais":["lait","mamelles"]}}