{"Deutsch":"etwas kennen wie seine Hosentasche  (Sprichw)","English":"to know sth like the back of one's hand (idiom)","h":[{"b":"ㄌㄧㄠˇ　ㄖㄨˊ　ㄓˇ　ㄓㄤˇ","d":[{"e":["`如~：「`他~`對~`國內~`職棒~`的~`發展~`情況~，`了如指掌~。」"],"f":"`比喻~`對~`事情~`了解~`得~`非常~`清楚~。`參見~「`瞭如指掌~」`條~。"}],"p":"liǎo rú zhǐ zhǎng"}],"t":"`了~`如~`指掌~","translation":{"Deutsch":["etwas kennen wie seine Hosentasche  (Sprichw)","etwas kennen wie seine Westentasche  (Sprichw)","wörtl. etwas so gut kennen wie seine eigene Hand  (Sprichw)"],"English":["to know sth like the back of one's hand (idiom)","to know (a person, a place etc) inside out"]}}