{"English":"lit. secondary foreigner","h":[{"b":"ㄦˋ　ㄇㄠˊ　˙ㄗ","d":[{"f":"`黑龍江~`一帶~`的~`土話~。`指~`兩~`歲~`的~`羊~。","q":["`清~．`西~`清~《`黑龍江~`外~`記~．`卷~`八~》：「`羊~`一~`歲~`謂~`之~`庫~`爾~`布~`子~，`二~`歲~`謂~`之~`二毛子~。」"]},{"f":"`清~`末~`義和團~`團員~`譏~`稱~`信~`耶穌教~`或~`辦理~`洋務~`的~`中國~`人~。","q":["《`恨海~．`第~`七~`回~》：「`只見~`街上~`往來~  `的~，`沒有~`一個~`不是~`義和團~，`擁擠~`的~`不堪~。`口~`中~`亂~`嚷~：『`燒~`教堂~！`燒~`使館~！`殺~`毛子~！`殺~`二毛子~！』」"]}],"p":"èr máo zi"}],"t":"`二毛~`子~","translation":{"English":["lit. secondary foreigner","(derogatory term for Chinese Christians and others associated with foreigners, used at the time of the Boxer Rebellion)","(coll.) westernized Chinese person","(derog.) person of mixed Chinese and Russian blood","(slang) Ukraine","German shepherd dog","(dialect) two-year-old goat"]}}