{"Deutsch":"Kommunikation  (S)","English":"to associate (with)","francais":"contact social","h":[{"b":"ㄐㄧㄠ　ㄨㄤˇ","d":[{"f":"`交際~`往來~。","q":["`晉~．`干寶~《`搜神記~．`卷~`一~`六~》：「`我~`女~`大聖~，`死~`經~`二~`十~`三~`年~，`猶~`能~`與~`生人~`交往~。」","`宋~．`蘇軾~〈`答~`孫~`志~`康~`書~〉：「`李~`太~`伯~`雖~`前輩~，`不相~`交往~，`然~`敬~`其~`人~。」"],"s":"`交遊~"}],"p":"jiāo wǎng"}],"t":"`交~`往~","translation":{"Deutsch":["Kommunikation  (S)","Bekanntschaften  (S)","Kommunikationssystem  (S)","Kontakt  (S)","Telekommunikation  (S)","Umgang  (S)","Verein  (S)","Verkehr  (S)","Vorstellung  (S)","Zugang  (S)","kommunizieren  (V)","umgehen  (V)"],"English":["to associate (with)","to have contact (with)","to hang out (with)","to date","(interpersonal) relationship","association","contact"],"francais":["contact social","fréquentation"]}}