{"Deutsch":"Arm in Arm ","English":"linking arms","h":[{"b":"ㄐㄧㄠ　ㄅㄧˋ","d":[{"f":"`拱手~。`多~`表示~`恭敬~、`降服~。","q":["《`戰國策~．`魏~`策~`二~》：「`魏~`不能~`支~，`交臂~`而~`聽~`楚~。」","《`南齊書~．`卷~`三八~．`蕭~`赤~`斧~`傳~》：「`莫不~`舉踵~`來~`王~，`交臂~`納貢~。」"]},{"f":"`舊時~`罪犯~`雙手~`被~`交叉~`綁~`在~`背後~，`稱~`為~「`交臂~」。","q":["《`莊子~．`天地~》：「`睆睆~`然~`在~`纏繳~`之~`中~，`而~`自~`以為~`得~，`則是~`罪人~`交臂~`歷~`指~，`而~`虎~`豹~`在於~`囊~`檻~，`亦~`可以~`為~`得~`矣~。」","《`漢書~．`卷~`四~`五~．`息~`夫~`躬~`傳~》：「`守~`相~`有~`罪~，`車~`馳~`詣闕~，`交臂~`就~`死~。」"]},{"f":"`胳臂~`靠~`著~`胳臂~。`表示~`親近~、`接近~。","q":["《`後漢書~．`卷~`七~`二~．`董卓~`傳~》：「`乃~`駢~`馬~`交臂~`相~`加~，`笑語~`良久~。」","`宋~．`蘇軾~〈`夜~`值~`祕~`閣~`呈~`王~`敏~`甫~〉`詩~：「`共~`誰~`交臂~`論~`今~`古~，`只有~`閑~`心~`對~`此~`居~。」"]},{"f":"`比喻~`知心~`的~`朋友~。","q":["`南朝~`宋~．`謝靈運~〈`感時~`賦~〉：「`相~`物類~`以~`迨~`已~，`閔~`交臂~`之~`匪~`賒~。」","`唐~．`駱賓王~〈`與~`博~`昌~`父老~`書~〉：「`自解~`攜~`襟~`袖~，`一~`十~`五~`年~，`交臂~`存亡~，`略~`無~`半~`在~。」"]}],"p":"jiāo bì"}],"t":"`交~`臂~","translation":{"Deutsch":["Arm in Arm "],"English":["linking arms","arm in arm","very close"]}}