{"Deutsch":"Mensch(en), Bevölkerung  (S)","English":"number of people in a family","francais":"population","h":[{"b":"ㄖㄣˊ　ㄉㄧㄥ","d":[{"f":"`能~`服役~`的~`成年~`男子~。","q":["《`新唐書~．`卷~`五~`二~．`食貨志~`二~》：「`租庸調~`之~`法~，`以~`人丁~`為~`本~。」"]},{"f":"`人口~。","q":["《`清史稿~．`卷~`一二~○．`食貨志~`一~》：「`康熙~`五~`十~`一~`年~，`有~『`新~`增~`人丁~`永~`不~`加~`賦~』`之~`諭~。」","《`紅樓夢~．`第~`二~`回~》：「`雨~`村~`笑~`道~：『`原來~`是~`他家~。`若~`論~`起來~，`寒~`族人~`丁~`卻不~`少~。』」"],"s":"`生齒~"},{"f":"`家僕~。","q":["《`紅樓夢~．`第~`五~`九~`回~》：「`賴~`大~`添~`派~`人丁~`上夜~，`將~`兩~`處~`廳~`院~`都~`關~`了~。」"]}],"p":"rén dīng"}],"t":"`人~`丁~","translation":{"Deutsch":["Mensch(en), Bevölkerung  (S)"],"English":["number of people in a family","population","(old) adult males","male servants"],"francais":["population","nombre des membres de famille"]}}