{"h":[{"b":"ㄔㄢˇ　ㄉㄧˋ","d":[{"f":"`依然~、`依舊~。","q":["`宋~．`陳~`允~`平~〈`丹~`鳳~`吟~．`暗~`柳~`煙~`深~`何處~〉`詞~：「`過了~`幾番~`花信~，`曉~`來~`剗地~`寒意~`惡~。」","`明~．`許~`三階~《`節~`俠~`記~．`第~`九~`齣~》：「`愁~`聽~`啼~`鳥~`頻~`求~`侶~，`憐~`知己~`剗地~`分離~。」"]},{"f":"`平白無故~。","q":["`宋~．`盧~`祖~`皋~〈`夜~`飛~`鵲~`慢~．`驕~`嘶~`破~`清曉~〉`詞~：「`牽~`衣~`搵~`彈~`淚~，`問~`淒風~`愁~`露~，`剗地~`東西~。」","《`董西廂~．`卷~`一~》：「`剗地~`相逢~，`引調~`得人~`來~`眼狂心熱~。」"]},{"f":"`怎的~，`為~`反詰~`語~。","q":["`宋~．`趙~`長~`卿~〈`滿江紅~．`懊惱~`平生~〉`詞~：「`記得~`當初~`低~`耳~`畔~，`是~`誰~`先~`有~`于飛~`約~。`惟~`到~`今~、`剗地~`誤~`盟~`言~，`還~`先~`惡~。」"]},{"f":"`反而~。","q":["`元~．`馬致遠~《`青衫淚~．`第~`二~`折~》：「`往常~`我~`春心~`寄~`錦~`箋~，`離情~`接~`斷~`絃~，`風流~`煞~`謝~`家庭~`院~。`到~`如今~`剗地~`教~`共~`豬~`狗~`同~`眠~。」"]}],"p":"chǎn dì"}],"t":"`剗~`地~"}