{"English":"half willing and half unwilling (idiom); to yield after making a show of resistance","francais":"(expr. idiom.) à moitié volontaire et à moitié réticent","h":[{"=":"012400009","b":"ㄅㄢˋ　ㄊㄨㄟ　ㄅㄢˋ　ㄐㄧㄡˋ","d":[{"a":"`投懷送抱~﹑`直捷~`爽快~","f":"`心中~`早已~`同意~，`表面上~`卻不~`答應~，`表現~`出~`假意~`推辭~`的~`姿態~。","q":["`元~．`王實甫~《`西廂記~．`第~`四~`本~．`第一~`折~》：「`半推半就~，`又~`驚~`又~`愛~。」","《`紅樓夢~．`第~`四~○`回~》：「`鴛鴦~`也~`半推半就~，`謝~`了~`坐~，`便~`坐下~。」"],"s":"`欲就還推~"}],"p":"bàn tuī bàn jiù"}],"t":"`半~`推~`半~`就~","translation":{"English":["half willing and half unwilling (idiom); to yield after making a show of resistance"],"francais":["(expr. idiom.) à moitié volontaire et à moitié réticent"]}}