{"Deutsch":"Südchinesisches Meer  (Geo)","English":"South China Sea","francais":"mer de Chine méridionale","h":[{"=":"161900023","b":"ㄋㄢˊ　ㄏㄞˇ","d":[{"f":"`泛指~`南方~`海域~。","q":["《`文選~．`潘尼~．`贈~`陸機~`出~`為~`吳~`王~`郎中~`令~`詩~》：「`振~`鱗~`南海~，`濯~`翼~`清流~。」"]},{"f":"`海洋~`名~。`自~`臺灣海峽~`經~`大陸地區~`福~`建~`南端~`至~`廣~`東~`之~`雷州半島~、`海南島~`一帶~`的~`海面~。"},{"f":"`北京~`三海~`之~`一~。`參見~「`三海~」`條~。"},{"f":"`縣~`名~。`位於~`大陸地區~`廣東省~`番禺縣~`西北~，`廣州市~`西南~。"}],"p":"nán hǎi"}],"t":"`南~`海~","translation":{"Deutsch":["Südchinesisches Meer  (Geo)","Nanhai  (Eig, Geo)"],"English":["South China Sea"],"francais":["mer de Chine méridionale"]}}