{"English":"to brag","francais":"vanter","h":[{"=":"483600011","b":"ㄔㄨㄟ　ㄒㄩ","d":[{"f":"`呼氣~、`噓~`氣~。","q":["《`隋書~．`卷~`七~`五~．`儒林~`傳~．`王~`孝~`籍~`傳~》：「`咳唾~`足以~`活~`枯~`麟~，`吹噓~`可~`用~`飛~`窮~`羽~。」","《`水滸傳~．`第一~`六~`回~》：「`那~`十~`個~`廂~`禁軍~，`雨~`汙~`通~`流~，`都~`嘆氣~`吹噓~。」"]},{"f":"`吹捧~、`稱揚~。","q":["`北齊~．`顏之推~《`顏氏家訓~．`名實~》：「`有~`一~`士族~，`讀書~`不過~`二~`三~`百~`卷~，`天才~`鈍~`拙~，`而~`家世~`殷~`厚~，`雅~`自矜~`持~，`多~`以~`酒~`犢~`珍玩~，`交~`諸~`名士~。`甘~`共~`餌~`者~，`遞~`共~`吹噓~。`朝廷~`以為~`文~`華~，`亦~`嘗~`出境~`聘~。」"]},{"f":"`比喻~`不費吹灰之力~`而~`能~`成就~`大事~。","q":["`南朝~`陳~．`徐陵~〈`檄~`周~`文~〉：「`叱吒~`而~`平~`宿~`豫~，`吹噓~`而~`定~`壽~`陽~。」","`明~．`張~`四維~《`雙~`烈~`記~．`第~`二~`七~`齣~》：「`吹噓~`定~`魯~`齊~，`談笑~`平~`吳~`楚~。」"]},{"f":"`風~`吹~。","q":["`唐~．`孟郊~〈`哭~`李~`觀~〉`詩~：「`清塵~`無~`吹噓~，`委~`地~`難~`飛揚~。」"]},{"f":"`比喻~`獎掖~`擢升~。","q":["`唐~．`杜甫~〈`贈~`獻~`納~`使~`起居~`田舍~`人~〉`詩~：「`揚雄~`更~`有~`河東~`賦~，`唯~`待~`吹噓~`送上天~。」"]},{"f":"`吹~`竽~。","q":["`北周~．`庾信~〈`小~`園~`賦~〉：「`昔~`草~`濫~`于~`吹噓~，`藉~`文言~`之~`慶~`餘~。」"]}],"p":"chuī xū"}],"t":"`吹~`噓~","translation":{"English":["to brag"],"francais":["vanter","flatter"]}}