{"English":"to gasp for breath","francais":"halètement","h":[{"=":"485300002","b":"ㄔㄨㄢˇ　ㄒㄧˊ","d":[{"f":"`呼吸~`困難~`或~`呼吸~`急促~`的~`樣子~。","q":["《`儒林外史~．`第~`二~○`回~》：「`挨~`到~`晚上~，`痰~`響~`了~`一陣~，`喘息~`一回~，`嗚呼哀哉~，`斷氣~`身亡~。」"]},{"e":["`如~：「`連~`加~`三~`天~`的~`班~，`讓~`我們~`稍~`作~`喘息~，`再~`繼續~`努力~。」"],"f":"`短暫~`的~`休息~，`以~`紓解~`疲勞~`和~`壓力~。"},{"f":"`比喻~`時間~`的~`短促~。","q":["《`後漢書~．`卷~`五~`六~．`張~`皓~`傳~》：「`荒裔~`愚人~，`不能~`自~`通~`朝廷~，`不堪~`侵~`枉~，`遂~`復~`相聚~`偷生~，`若~`魚遊釜中~，`喘息~`須臾~`閒~`耳~。」"]}],"p":"chuǎn xí"}],"t":"`喘~`息~","translation":{"English":["to gasp for breath","to take a breather"],"francais":["halètement"]}}