{"Deutsch":"strenge od. grimmige Kälte, bitter kalt ","English":"bitter cold","francais":"froid rigoureux","h":[{"=":"609500010","b":"ㄧㄢˊ　ㄏㄢˊ","d":[{"a":"`酷暑~,`酷熱~,`熾熱~,`炎暑~,`炎熱~","f":"`非常~`寒冷~。","q":["《`文選~．`阮籍~．`詠懷~`詩~`一~`七~`首~`之~`一二~》：「`朔風~`厲~`嚴寒~，`陰氣~`下~`微~`霜~。」","《`三國演義~．`第~`三七~`回~》：「`時值~`隆冬~，`天氣~`嚴寒~，`彤雲~`密布~。」"],"s":"`冰冷~,`酷寒~,`寒冬~,`極~`冷~"}],"p":"yán hán"}],"t":"`嚴~`寒~","translation":{"Deutsch":["strenge od. grimmige Kälte, bitter kalt "],"English":["bitter cold","severe winter"],"francais":["froid rigoureux"]}}