{"Deutsch":"verhängt ","English":"to declare","francais":"proclamer","h":[{"=":"415600001","b":"ㄒㄩㄢ　ㄅㄨˋ","d":[{"f":"`公開~`告示~，`使~`眾人~`都~`知道~。《`周禮~．`秋官~．`小~`司寇~》：「`乃~`宣布~`于~`四方~，`憲~`刑~`禁~。」《`文選~　．`王襃~．`四~`子~`講~`德~`論~》：「`宣布~`詔書~，`勞來~`不~`怠~，`令~`百姓~`遍~`曉~`聖~`德~。」`也~`作~「`宣~`佈~」。","s":"`頒發~,`發表~,`公布~,`公告~,`宣告~"},{"f":"`宣揚~`流布~。《`宋書~．`卷~`七~`五~．`顏~`竣~`傳~》：「`竣~`在~`彭城~`常~`向~`親人~`敘~`之~，`言~`遂~`宣布~，`聞~`於~`太~　`祖~。」《`文選~．`王襃~．`四~`子~`講~`德~`論~》：「`所謂~`中和~`樂~`職~`宣布~`之~`詩~，`益州~`刺史~`之~`所~`作~`也~。」　`也~`作~「`宣~`佈~」。"}],"p":"xuān bù"}],"t":"`宣~`布~","translation":{"Deutsch":["verhängt ","Ankündigung  (S)","Verkündung  (S)","anmelden  (V)","erklären  (V)","erklärt  (V)","verhängen  (V)","verkünden  (V)"],"English":["to declare","to announce","to proclaim"],"francais":["proclamer","annoncer"]}}