{"h":[{"b":"ㄒㄧㄠˇ　ㄌㄤˊ","d":[{"f":"`稱謂~。`婦人~`稱~`丈夫~`的~`弟弟~。","q":["`南朝~`宋~．`劉義慶~《`世說新語~．`規~`箴~》：「`昔~`夫人~`臨終~，`以~`小~　`郎~`囑~`新婦~，`不以~`新婦~`囑~`小郎~。」","《`聊齋志異~．`卷~`五~．`閻王~》：「`自當~`是~`小郎~`大好~`乾綱~，`到~`不得~`代~`哥子~`降伏~`老媼~。」"]},{"f":"`對~`年輕~`男子~`的~`尊稱~，`意~`同~`少爺~。","q":["《`水滸傳~．`第~`三七~`回~》：「`小郎~`已~`自~`都~`分付~`了~，`我們~`如何~`敢~`賣~`與~`你們~`吃~。」"]},{"f":"`年輕~`的~`僮僕~。","q":["《`喻世明言~．`卷~`一~．`蔣~`興~`哥~`重~`會~`珍珠~`衫~》：「`陳~`大郎~`情懷~`撩亂~，`忙忙~`的~`收拾~`銀兩~，`帶~`個~`小郎~，`再~`望~`襄~`陽~`舊~`路~`而~`進~。」"]}],"p":"xiǎo láng"}],"t":"`小~`郎~"}