{"Deutsch":"wenig  (Adj)","English":"few","c":4,"francais":"peu","h":[{"=":"4994","b":"ㄕㄠˇ","d":[{"e":["`如~：「`稀少~」、「`和平日~`相比~，`她~`今天~`的~`話~`好像~`少~`了~`一點~。」"],"f":"`不多~。","type":"`形~"},{"e":["`如~：「`米~`麵~`是~`一天~`不可~`少~`的~。」、「`少~`了~`一個~`人~，`不知~`有~`沒有~`候補~`的~？」"],"f":"`短缺~、`不夠~。","type":"`動~"},{"e":["`如~：「`五~`比~`八~`少~`三~。」"],"f":"`二~`數~`相較~`的~`差~。","type":"`動~"},{"e":["`如~：「`我~`屋裡~`少~`了~`幾~`件~`東西~，`你們~`知~`不知道~？」"],"f":"`丟失~、`遺失~。","type":"`動~"},{"f":"`輕視~、`不滿~。","q":["《`史記~．`卷~`六~`九~．`蘇秦~`傳~》：「`顯~`王~`左右~`素~`習~`知~`蘇秦~，`皆~`少~`之~，`弗~`信~。」"],"type":"`動~"},{"f":"`不久~、`短~`時間~。","q":["《`孟子~．`萬~`章~`上~》：「`始~`舍~`之~，`圉圉~`焉~，`少~`則~`洋洋~`焉~，`攸~`然而~`逝~。」"],"type":"`副~"},{"e":["`如~：「`這~`是~`少有~`的~`事~。」"],"f":"`不經~`常~`的~。","type":"`副~"},{"f":"`略微~、`稍微~。","q":["《`莊子~．`徐~`无~`鬼~》：「`今~`予~`病~`少~`痊~，`予~`又~`且~`復~`遊~`於~`六合~`之外~。」","《`史記~．`卷~ `一一○~．`匈奴~`傳~》：「`兒~`能~`騎~`羊~，`引~`弓~`射~`鳥~`鼠~；`少~`長~`則~`射~`狐~`兔~，`用~`為~`食~。」"],"type":"`副~"}],"p":"shǎo"},{"=":"4995","b":"ㄕㄠˋ","d":[{"e":["`如~：「`少~`男~」、「`少女~」、「`少爺~」。"],"f":"`年幼~`的~、`年輕~`的~。","type":"`形~"},{"f":"`幼年~`或~`年輕~`的~`時候~。","q":["《`墨子~．`兼愛~`中~》：「`少~`失~`其~`父母~`者~，`有~`所~`放~`依~`而~`長~。」","`三國~`魏~．`嵇康~〈`與~`山~`巨~`源~`絕交~`書~〉：「`此~`由~`禽~`鹿~，`少見~`馴~`育~，`則~`服從~`教~`制~。」"],"type":"`名~"},{"f":"`年輕~`的~`人~。","q":["《`晉書~．`卷~`八~○．`列傳~．`王羲之~》：「`王~`氏~`諸~`少~`並~`佳~。」","《`儒林外史~》`第~`四~`一回~：「`那些~`好事~`的~`惡少~，`都~`一~`傳~`兩~，`兩~`傳~`三~`的~`來~`物色~，`非~`止~`一日~。」"],"type":"`名~"},{"f":"`姓~。`如~`漢~`代~`有~`少年~`唯~。","type":"`名~"}],"p":"shào"}],"n":1,"r":"`小~","t":"少","translation":{"Deutsch":["wenig  (Adj)"],"English":["few","less","to lack","to be missing","to stop (doing sth)","seldom","young"],"francais":["peu","quelque","manquer de","jeune"]}}