{"Deutsch":"behandeln  (Med)","English":"treatment","francais":"traitement","h":[{"b":"ㄉㄞˋ　ㄩˋ","d":[{"f":"`對待~、`接待~。","q":["《`南史~．`卷~`六~`四~．`王~`琳~`傳~》：「`雖~`本~`圖~`不遂~，`齊人~`亦~`以此~`重~`之~，`待遇~`甚~`厚~。」","《`五代史~`平話~．`唐~`史~．`卷~`上~》：「`晉~`王~`好生~`待遇~`他~，`遣人~`招~`誘~`王~`彥~`章~`歸~`晉~。」"]},{"e":["`如~：「`這~`職務~`待遇~`很~`高~。」"],"f":"`工作~`的~`報酬~。`指~`薪俸~。"}],"p":"dài yù"}],"t":"`待~`遇~","translation":{"Deutsch":["behandeln  (Med)"],"English":["treatment","pay","salary","status","rank"],"francais":["traitement","rémunération"]}}