{"Deutsch":"Nachkommen  (S)","English":"descendant","francais":"postérité","h":[{"=":"274600006","b":"ㄏㄡˋ　ㄉㄞˋ","d":[{"a":"`前代~　2.`前輩~,`祖先~","f":"`後世~，`未來~`的~`世代~。","q":["《`漢書~．`卷~`九九~．`王莽~`傳~`上~》：「`今~`帝~`以~`幼年~`復~`奉~`大宗~，`為~`成~`帝~`後~，`宜~`明~`一統~`之~`義~，`以~`戒~`前事~，`為~`後代~`法~。」","《`文選~．`劉琨~．`勸進~`表~》：「`前事~`不~`忘~，`後代~　`之~`元~`龜~`也~。」"]},{"f":"`後裔~、`子孫~。","q":["《`文選~．`揚雄~．`長楊~`賦~》：「`又~`恐~`後代~`迷~`於~`一時~`之~`事~，`常~`以此~`為~`國家~`之~`大務~，`淫~`荒~`田獵~，`陵夷~`而~`不~`禦~`也~。」","《`初~`刻~`拍案驚奇~．`卷~`二四~》：「`燒香~`祈禱~，`不論~`男女~，　`求生~`一個~，`以~`續後~`代~。」"]}],"p":"hòu dài"}],"t":"`後~`代~","translation":{"Deutsch":["Nachkommen  (S)","Nachkommenschaft  (S)","Nachwelt  (S)"],"English":["descendant","progeny","posterity","later ages","later generations"],"francais":["postérité","descendance"]}}