{"Deutsch":"Inflammation  (S)","English":"rage","francais":"courroux","h":[{"=":"171400008","b":"ㄋㄨˋ　ㄏㄨㄛˇ","d":[{"f":"`熊熊~`燃燒~`的~`火焰~。","q":[" `宋~．`王~`邁~〈`再~`呈~`趙~`倅~〉`詩~：「`虛舟~`相~`觸~`何~`心~`在~，`怒火~`雖~`炎~`一餉~`空~。」"]},{"e":["`如~：「`他~`在~`連番~`受辱~`之後~，`終於~`壓不住~`心中~`的~`怒火~，`做~`出~`強烈~`的~`反擊~。」"],"f":"`如~`火焰~`般~`強烈~`的~`憤怒~`情緒~。","q":["《`隋~`唐~`演義~》`第一~`二~`回~：「`因~`有~`滿~`桌子~`的~`銀子~，`不道~`人~`來~`拿~`他~，`只道~`歹人~`進來~`搶劫~，`怒火~`直~`衝~，`動手~`就~`打~。」"]}],"p":"nù huǒ"}],"t":"`怒~`火~","translation":{"Deutsch":["Inflammation  (S)"],"English":["rage","fury","hot anger"],"francais":["courroux","feu"]}}