{"Deutsch":"bedauern, Bedauern  (S)","English":"regret (sense of loss or dissatisfaction)","c":16,"francais":"regret","h":[{"=":"2774","b":"ㄏㄢˋ","d":[{"f":"`怨恨~。","q":["《`玉篇~．`心~`部~》：「`憾~，`恨~`也~。」","`南朝~`宋~．`劉義慶~《`世說新語~．`德行~》：「`既~`還~，`知~`母~`撼~`之~`不已~，`因~`跪~`前~`請~`死~。」","《`新唐書~．`卷~`一一~`七~．`劉~`褘~`之~`傳~》：「`子~`翼~`詈~`人~，`人~`都~`不~`憾~。」"],"type":"`動~"},{"e":["`如~：「`缺憾~」、「`遺憾~」、「`抱憾~`而~`終~」。"],"f":"`心中~`不~`完滿~`的~`感覺~。","q":["《`左傳~．`襄~`公~`二~`十~`九~`年~》：「`美~`哉~！`猶~`有~`憾~。」","《`孟子~．`梁惠王~`上~》：「`是~`使~`民~`養生~`喪~`死~`無憾~`也~。」"],"type":"`名~"},{"e":["`如~：「`憾事~」。"],"f":"`悔恨~`的~、`不滿~`意~`的~。","type":"`形~"}],"p":"hàn"}],"n":13,"r":"`心~","t":"憾","translation":{"Deutsch":["bedauern, Bedauern  (S)"],"English":["regret (sense of loss or dissatisfaction)"],"francais":["regret","regretter"]}}