{"Deutsch":"Erfolg oder Misserfolg  (S)","English":"success or failure","francais":"succès ou échec","h":[{"=":"478200001","b":"ㄔㄥˊ　ㄅㄞˋ","d":[{"f":"`成功~`與~`失敗~。","q":["《`文選~．`嵇康~．`與~`山~`巨~`源~`絕交~`書~》：「`載籍~`既~`記~`其~`成敗~，`古今~`又~`著~`其~`愚~`智~`矣~！」","《`三國演義~．`第一~`一~`五~`回~》：「`成敗~`之~`事~，`在此一舉~，`汝~`等~`始終~`勿~`改~，`如~`有~`言~`退~`者~`立~`斬~。」"]},{"f":"`造成~`失敗~。","q":["《`後漢書~．`卷~`六~`九~．`何進~`傳~》：「`先帝~`嘗~`與~`太后~`不快~，`幾~`至~`成敗~。`我曹~`涕泣~`救解~，`各~`出家~`財~`千萬~`為~`禮~，`和悅~`上~`意~，`但~`欲~`託~`卿~`門戶~`耳~。」"]}],"p":"chéng bài"}],"t":"`成~`敗~","translation":{"Deutsch":["Erfolg oder Misserfolg  (S)"],"English":["success or failure"],"francais":["succès ou échec"]}}