{"Deutsch":"Aufschub, Verschiebung  (S)","English":"to postpone","francais":"remettre","h":[{"b":"ㄊㄨㄟ　ㄔˊ","d":[{"a":"`提前~","e":["`如~：「`趕快~`把~`企劃~`案~`擬~`出來~，`別~`藉故~`推遲~。」"],"f":"`延遲~。`把~`預定~`的~`時間~`往後~`延~。"}],"p":"tuī chí"}],"t":"`推~`遲~","translation":{"Deutsch":["Aufschub, Verschiebung  (S)","etw verschieben, etw aussetzen  (S)","etw auf die lange Bank schieben  (V)","etw aufschieben, hinauszögern  (V)","etw aussetzen  (Adj)"],"English":["to postpone","to put off","to defer"],"francais":["remettre","ajourner"]}}