{"English":"to choose which Buddha to burn incense to (idiom); fig. to curry favor from the right person","h":[{"b":"ㄐㄧㄢˇ　ㄈㄛˊ　ㄕㄠ　ㄒㄧㄤ","d":[{"f":"`選擇~`佛~`的~`大小~`而~`燒~`不同~`的~`香~。`語~`本~《`全唐詩~．`卷~`八~○`六~．`寒山~`詩~》：「`擇~`佛~`燒~`好~`香~，`揀~`僧~`歸~`供養~。」`比喻~`待人~`有~`厚薄~`之~`分~。《`品花寶鑑~．`第一~`八~`回~》：「`府~`中~`那些~`朋友~`門客~`及~`家人~`們~，`算起來~`就~`有~`幾~`百~`人~，`那~`一天~`沒有~`些~`事~，`應酬~`慣~`了~，`是~`不能~`揀佛燒香~`的~。」"}],"p":"jiǎn fó shāo xiāng"}],"t":"`揀~`佛~`燒香~","translation":{"English":["to choose which Buddha to burn incense to (idiom); fig. to curry favor from the right person"]}}