{"Deutsch":"Sonnenfinsternis (S, Astron)","English":"solar eclipse","francais":"Éclipse solaire","h":[{"b":"ㄖˋ　ㄕˊ","d":[{"a":"`月食~","f":"`月球~`運行~`到~`太陽~`與~`地球~`的~`中間~，`則~`太陽~`的~`光~`被~`月球~`遮擋~，`無法~`射~`到~`地球~`上~，`這~`種~`現象~  `稱~`為~「`日食~」。`也~`作~「`日蝕~」。"},{"f":"`每日~`的~`飲食~。`引申~`為生~`活~。","q":["《`儒林外史~．`第~`五~`五~`回~》：「`又~`過半~`年~，`日食~`艱難~，`把~`大房~`子~`賣~`了~，`搬~`在~`一~`所~`小房~`子~`住~。」"]}],"p":"rì shí"}],"t":"`日~`食~","translation":{"Deutsch":["Sonnenfinsternis (S, Astron)"],"English":["solar eclipse"],"francais":["Éclipse solaire"]}}