{"English":"to correct in the evening a fault of the morning (idiom)","h":[{"b":"ㄓㄠ　ㄍㄨㄛˋ　ㄒㄧˋ　ㄍㄞˇ","d":[{"f":"`早上~`犯~`的~`過失~，`到~`晚上~`就~`改正~`了~。`語~`本~《`大戴禮記~．`曾子~`立事~》：「`朝~`有~`過~，`夕~`改~`則~`與~`之~；`夕~`有~`過~，`朝~`改~`則~`與~`之~。」`比喻~`及時~`改過~。《`漢書~．`卷~`八~`四~．`翟~`方~`進~`傳~》：「`朝過夕改~，`君子~`與~`之~，`君~`何~`疑~`焉~？」`唐~．`陸贄~〈`奉~`天~`改元~`大赦~`制~〉：「`況~`黜免~`之~`徒~，`沉鬱~`既~`久~，`朝過夕改~，`仁~`何~`遠~`哉~！」"}],"p":"zhāo guò xì gǎi"}],"t":"`朝~`過~`夕~`改~","translation":{"English":["to correct in the evening a fault of the morning (idiom)","to quickly amend one's ways"]}}