{"Deutsch":"Zimtkassie ","English":"Chinese cinnamon (Cinnamonum cassia)","francais":"cannelle de Chine","h":[{"b":"ㄍㄨㄟˋ　ㄆㄧˊ","d":[{"f":"`植物~`名~。`樟~`科~`樟~`屬~，`常~`綠~`喬木~。`葉~`披~`針~`形~，`革~`質~`互生~，`表面~`綠色~`無~`毛~，`背面~`有~`顯著~`倒~`生~`絹~`毛~。`圓~`錐~`花叢~`出~`自新~`枝節~`上~，`有~`花~`十~～`十~`二~`朵~，`花被~`具~`短~`筒~，`有~`六~`倒~`卵~`狀~`裂片~；`花柱~`粗~`肥~，`柱頭~`大~`而~`為頭~`狀~。`核果~`橢圓形~，`平滑~`無~`毛~，`花被~`宿~`存~`為~`半球~`形~。`樹皮~`可作~`香料~、`藥用~。"}],"p":"guì pí"}],"t":"`桂~`皮~","translation":{"Deutsch":["Zimtkassie ","Zimt  (S)","Zimtbaum  (S)"],"English":["Chinese cinnamon (Cinnamonum cassia)","cassia bark"],"francais":["cannelle de Chine","Cinnamomum cassia","écorce de cassia"]}}