{"English":"to have an imposing or impressive appearance","francais":"apparence imposante ou impressionnante","h":[{"=":"357600044","b":"ㄑㄧˋ　ㄩˇ　ㄒㄩㄢ　ㄤˊ","d":[{"a":"`萎靡不振~,`委靡不振~","f":"`形容~`人~`的~`神采~`洋溢~，`氣度~`不凡~。《`初~`刻~`拍案驚奇~．`卷~`一~○》：「`朝霞~`見~`韓~`生~`氣宇軒昂~，`丰神~`俊~`朗~，`才貌~`甚是~`相當~，`那裡~`管~`他家~`貧~？」《`儒林外史~．`第~`三~`四~`回~》：「`莊~`紹~`光~`見~`蕭~`昊~`軒~`氣宇軒昂~，`不同~`流俗~，`也~`就~`著實~`親近~。」`也~`作~「`器宇軒昂~」、「`軒昂氣宇~」。","s":"`高~`視~`睨~`步~,`高視闊步~,`精神抖擻~,`神采飛揚~,`神采奕奕~,`容光煥發~"}],"p":"qì yǔ xuān áng"}],"t":"`氣宇~`軒昂~","translation":{"English":["to have an imposing or impressive appearance","impressive appearance","straight and impressive looking"],"francais":["apparence imposante ou impressionnante"]}}