{"Deutsch":"Quelle  (S)","English":"water source","francais":"source","h":[{"=":"516300109","b":"ㄕㄨㄟˇ　ㄩㄢˊ","d":[{"f":"`河流~`發源~`的~`地方~。","q":["`晉~．`陶淵明~〈`桃花源記~〉：「`復~`前行~，`欲~`窮~`其~`林~，`林~`盡~`水源~，`便得~`一~`山~。」","`唐~．`劉長卿~〈`尋~`南~`溪~`常山~`道人~`隱居~〉`詩~：「`過~`雨~`看~`松~`色~，`隨~`山~`到~`水源~。」"]},{"f":"`灌溉~`用水~`或~`飲用~`水~`等~`的~`來源~。"}],"p":"shuǐ yuán"}],"t":"`水~`源~","translation":{"Deutsch":["Quelle  (S)"],"English":["water source","water supply","headwaters of a river"],"francais":["source","source d'un cours d'eau"]}}