{"Deutsch":"Feuerwerk (S)","English":"fireworks","francais":"feu d'artifice","h":[{"=":"6079000051","b":"ㄧㄢ　ㄏㄨㄚ","d":[{"f":"`春天~`繁~`花~`盛開~，`一片~`如~`煙~`如~`霧~`的~`樣子~。","q":["`唐~．`李白~〈`黃鶴樓~`送~`孟浩然~`之~`廣~`陵~〉`詩~：「`故人~`西~`辭~`黃鶴樓~，`煙花~`三~`月~`下~`揚州~。」"]},{"f":"`形容~`繁華~`的~`景象~。","q":["`唐~．`杜甫~〈`清明~〉`詩~`二~`首~`之~`二~：「`秦~`城樓~`閣~`煙花~`裡~，`漢~`主~`山河~`錦繡~`中~。」"]},{"f":"`稱~`娼妓~。","q":["`元~．`張~`壽~`卿~《`紅~`梨~`花~．`第~`四~`折~》：「`當初~`你~`寄書~`來~，`要~`見~`謝~`金蓮~，`元~`來~`是~`個~`妓女~。`我~`怕~`你~`迷戀~`煙花~，`墮~`了~`你~`進取~`之~`志~。」","《`初~`刻~`拍案驚奇~．`卷~`一二~》：「`當機~`兵~，`養~`娼妓~，`接~`子弟~`的~，`是~`個~`煙花~`的~`領袖~，`烏龜~`的~`班頭~。」"]}],"p":"yān huā"}],"t":"`煙~`花~","translation":{"Deutsch":["Feuerwerk (S)","Prostituierte (S)"],"English":["fireworks","prostitute (esp. in Yuan theater)"],"francais":["feu d'artifice"]}}