{"Deutsch":"Examensbester  (S)","English":"top scorer in the palace examination (highest rank of the Imperial examination system)","francais":"le premier à un l'examen","h":[{"=":"459600004","b":"ㄓㄨㄤˋ　ㄩㄢˊ","d":[{"f":"`我國~`古代~`科舉~`制度~`中~，`殿試~`一~`甲~`第一名~。","q":["《`五代史~`平話~．`梁~`史~．`卷~`上~》：「`探聽~`得~`試院~`開~`榜~`了~，`卻是~`別人~`做~`了~`狀元~，`別人~`做~`了~`榜眼~，`別人~`做~`了~`探花郎~。」","《`儒林外史~．`第~`二~`回~》：「`點~`了~`一本~`戲~，`是~`梁~`灝~`八~`十~`歲~`中狀元~`的~`故事~。」"]},{"f":"`稱~`現在~`各類~`考試~`中的~`榜首~。"}],"p":"zhuàng yuán"}],"t":"`狀~`元~","translation":{"Deutsch":["Examensbester  (S)"],"English":["top scorer in the palace examination (highest rank of the Imperial examination system)","see `榜眼~[bang3 yan3] and `探花~[tan4 hua1]","top scorer in college entrance examination `高考~[gao1 kao3]","(fig.) the most brilliantly talented person in the field","leading light"],"francais":["le premier à un l'examen"]}}