{"Deutsch":"logisches Denken  (S)","English":"logical thinking","h":[{"=":"188000010","b":"ㄌㄧˇ　ㄌㄨˋ","d":[{"f":"`道理~、`理論~。","q":["`明~．`謝~`榛~《`四~`溟~`詩話~．`卷~`一~》：「`宋~`人~`必~`先~`命意~，`涉~`於~`理路~，`殊~`無~`思致~。」","《`老殘遊記~．`第一~`回~》：「`章~`伯~`一~`想~，`理路~`卻~`也~`不錯~。」"]},{"f":"`思想~`或~`文章~`的~`條理~。","q":["`清~．`王~`士~`禎~《`池~`北~`偶~`談~．`卷~`一~`三~．`時文~`詩~`古文~》：「`時文~`雖~`無~`與~`詩~、`古文~，`然~`不解~`八股~，`即~`理路~`終~`不分~`明~。」"]}],"p":"lǐ lù"}],"t":"`理~`路~","translation":{"Deutsch":["logisches Denken  (S)"],"English":["logical thinking"]}}