{"Deutsch":"verlassen, ausräumen ","English":"to scatter","francais":"évacuer","h":[{"=":"511000010","b":"ㄕㄨ　ㄙㄢˋ","d":[{"a":"`集中~","e":["`如~：「`大樓~`突然~`發生~`火警~，`警~`方~`緊急~`疏散~`人群~。」"],"f":"`把~`密集~`的~`人員~、`物質~、`裝備~`分散~`開~。"},{"f":"`不受~`拘~`羈~。","q":["`南朝~`宋~．`謝靈運~〈`過~`白~`岸~`亭~〉`詩~：「`未若~`長~`疏散~，`萬事~`恆~`抱朴~。」","《`董西廂~．`卷~`一~》：「`攜~`一~`壺~`兒~`酒~，`戴~`一~`枝兒~`花~。`醉~`時~`歌~，`狂~`時~`舞~，`醒~`時~`罷~。`每日~`價~`疏散~`不曾~`著~`家~。」"]},{"f":"`疏遠~`離散~。","q":["`唐~．`李白~〈`東~`武~`吟~〉：「`賓友~`日~`疏散~，`玉~`樽~`亦~`已~`空~。」"]},{"f":"`驅散~。","q":["《`紅樓夢~．`第一~`九~`回~》：「`不過~`偶感~`風寒~，`吃~`一~`兩~`劑~`藥~`疏散~`疏散~`就~`好~`了~。」"]}],"p":"shū sàn"}],"t":"`疏~`散~","translation":{"Deutsch":["verlassen, ausräumen ","zerlegen, zerstreuen ","zerstreuen, verbreiten ","Evakuierung  (S)","Räumung  (S)","evakuieren  (V)","versprengen  (V)"],"English":["to scatter","to disperse","to evacuate","scattered","to relax"],"francais":["évacuer","disperser","clairsemé","épars","éparpillé"]}}