{"Deutsch":"Ausnutzen eines Sicherheitsproblems von Software  (S)","English":"to exploit","francais":"exploiter (par les prêts usuraires)","h":[{"b":"ㄆㄢˊ　ㄅㄛ","d":[{"e":["`如~：「`盤剝~`取利~」、「`盤剝~`無度~」。"],"f":"`輾轉~`剝削~。","s":"`剝削~"},{"f":"`搬運~`裝卸~`貨品~。","q":["《`六部~`成語~`註~`解~．`戶部~》：「`盤剝~：`將~`大船~`重~`載~`之~`米~`取~`出~`分~`載~`於~`小~`船~`之~`上~。」"]}],"p":"pán bō"}],"t":"`盤~`剝~","translation":{"Deutsch":["Ausnutzen eines Sicherheitsproblems von Software  (S)"],"English":["to exploit","to practice usury"],"francais":["exploiter (par les prêts usuraires)"]}}