{"English":"the tomb of the first emperor at Mt Li `驪山~|骊`山~[Li2 shan1] near Xi'an (awaits excavation)","h":[{"b":"ㄑㄧㄣˊ　ㄕˇ　ㄏㄨㄤˊ　ㄌㄧㄥˊ","d":[{"f":"`秦始皇~`葬~`處~。`位於~`今~`陝西省~`臨~`潼~`縣~`東~。`冢~`中~`作~`宮觀~`及~`百官~`位次~，`奇~`器~`珍怪~`充滿~`墓~`中~，`令~`匠作~`機~`弩~`矢~，`有~`接近~`者~`即~`射~`之~；`以~`水銀~`為~`百川~`江~`河~，`以~`人魚~`膏~`為~`燭~，`上~`具~`天文~，`下~`具~`地理~。`大事~`畢~，`盡~`閉~`工匠~，`無~`復出~`者~，`外~`樹~`草木~`以~`象山~。`見~《`史記~．`卷~`六~．`秦始皇~`本紀~》。"}],"p":"qín shǐ huáng líng"}],"t":"`秦始皇~`陵~","translation":{"English":["the tomb of the first emperor at Mt Li `驪山~|骊`山~[Li2 shan1] near Xi'an (awaits excavation)"]}}