{"Deutsch":"Abkürzung  (S)","English":"reduced fraction (e.g. one half for three sixths)","h":[{"=":"6522000021","b":"ㄩㄝ　ㄈㄣ","d":[{"f":"`數學~`上~`指~：(1) `分數~`的~`分母~`分子~，`同~`以~`一~`公因數~`除~`之~。`如~ 6/8=3/4。(2) `分~`式~`的~`分母~`分子~，`同~`以~`一~`公因式~`除~`之~。`如~(x²-1)/(ｘ-1)=ｘ+１。"}],"p":"yuē fēn"}],"t":"`約~`分~","translation":{"Deutsch":["Abkürzung  (S)","abkürzen  (V)"],"English":["reduced fraction (e.g. one half for three sixths)","to reduce a fraction by canceling common factors in the numerator and denominator"]}}