{"English":"lit. foul wind and bloody rain (idiom)","francais":"littéralement : vent puant le carnage (la viande crue) et pluie de sang","h":[{"b":"ㄒㄧㄥ　ㄈㄥ　ㄒㄧㄝˋ　ㄩˇ","d":[{"f":"`形容~`殺戮~`的~`慘酷~。`如~：「`獨裁者~`上臺~`之後~，`便~`整肅~`異己~，`掀起~`一片~`腥風血雨~。」`也~`作~「`血~`浪~`腥風~」、「`血雨腥風~」。"}],"p":"xīng fēng xiè yǔ"}],"t":"`腥風~`血~`雨~","translation":{"English":["lit. foul wind and bloody rain (idiom)","fig. reign of terror","carnage"],"francais":["littéralement : vent puant le carnage (la viande crue) et pluie de sang","figuré : règne de la terreur","carnage","massacre"]}}