{"English":"mistaken","c":6,"francais":"mésaventure","h":[{"=":"4852","b":"ㄔㄨㄢˇ","d":[{"f":"`乖違~、`違背~。","q":["`南朝~`梁~．`劉勰~《`文心雕龍~．`諸子~》：「`嗟夫~`身~`與~`時~`舛~，`志~`共~`道~`申~，`標~`心~`於~`萬古~`之~`上~，`而~`送~`懷~`於~`千載~`之~`下~。」"],"type":"`動~"},{"f":"`不順~`利~、`困厄~。","q":["`唐~．`王勃~〈`滕王閣序~〉：「`嗟乎~！`時運~`不~`齊~，`命途多舛~。」"],"type":"`形~"},{"f":"`錯誤~、`錯亂~。","q":["`南朝~`梁~．`沈約~〈`齊~`故~`安~`陸~`昭~`王~`碑文~〉：「`刑政~`繁~`舛~，`舊~`難~`詳~`一~。」","《`新唐書~．`卷~`一~`九~`六~．`隱逸~`傳~．`陸龜蒙~`傳~》：「`借~`人~`書~，`篇~`帙~`壞~`舛~，`必~`為~`輯~`褫~`刊~`正~。」"],"type":"`形~"},{"f":"`二~`一~`四部~`首~`之~`一~。","type":"`名~"}],"p":"chuǎn"}],"n":0,"r":"`舛~","t":"舛","translation":{"English":["mistaken","erroneous","contradictory"],"francais":["mésaventure","contretemps"]}}