{"English":"bud","c":9,"francais":"jonc","h":[{"=":"0091","b":"ㄅㄠ","d":[{"e":["`如~：「`含苞待放~」。"],"f":"`花~`蒂~`上~`包~`著~`未開~`花朵~`的~`小葉~`片~。","type":"`名~"},{"f":"`蓆~`草~。`可~`用來~`編織~`席子~、`草鞋~`等~。","type":"`名~"},{"f":"`將~`東西~`包裹~`起來~。","l":["`通~「`包~」。"],"type":"`動~"},{"f":"`容納~。","q":["《`文選~．`左思~．`魏~`都~`賦~》：「`巷~`苞~`諸~`公~，`都護~`之~`堂~，`殿~`居~`綺窗~。」"],"type":"`動~"},{"f":"`總攬~。","q":["《`文選~．`何晏~．`景福~`殿~`賦~》：「`兼~`苞~`博~`落~，`不常~`一~`象~。」"],"type":"`動~"},{"e":["`如~：「`竹苞松茂~」。"],"f":"`草木~`茂盛~。","type":"`形~"}],"p":"bāo"}],"n":5,"r":"`艸~","t":"苞","translation":{"English":["bud","flower calyx","luxuriant","profuse"],"francais":["jonc","dense"]}}