{"Deutsch":"unanständig, unhöflich ","English":"thick weeds","c":11,"francais":"herbe","h":[{"=":"0671","b":"ㄇㄤˇ","d":[{"f":"`植物~`名~。`八角茴香~`科~`莽草~`屬~，`常~`綠~`灌木~。`葉~`橢圓形~，`有~`香氣~，`葉~`面~`有~`細微~`小~`點~。`花瓣~`細長~，`黃白~`色~。`種子~`褐色~、`平滑~，`有~`劇毒~，`誤~`食~`能~`致死~。","type":"`名~"},{"f":"`叢生~`的~`草地~。","q":["《`文選~．`宋玉~．`風~`賦~》：「`蹶石伐木~，`梢~`殺~`林莽~。」","《`聊齋志異~．`卷~`一~．`賈~`兒~》：「`兒~`薄暮~`潛入~`何~`氏~`園~，`伏莽~`中~，`將~`以~`探~`狐~`所在~。」"],"type":"`名~"},{"e":["`如~：「`莽夫~」、「`莽漢~」、「`魯莽~」。"],"f":"`粗率~、`冒失~`的~。","type":"`形~"}],"p":"mǎng"}],"n":7,"r":"`艸~","t":"莽","translation":{"Deutsch":["unanständig, unhöflich ","Mang  (Eig, Fam)"],"English":["thick weeds","luxuriant growth","Illicium anisatum, a shrub with poisonous leaves","impertinent"],"francais":["herbe","campagne"]}}