{"Deutsch":"in Schwärmen kommen, wimmeln  (V)","English":"to flock (to see)","francais":"se presser en foule désordonnée","h":[{"=":"091800006","b":"ㄈㄥ　ㄩㄥˇ","d":[{"e":["`如~：「`蜂擁~`而~`來~」。"],"f":"`比喻~`人~`多~`而~`擁擠~。","q":["《`文明~`小史~．`第~`三~`回~》：「`眾人~`見~`洋人~`果然~`不在~`店~`內~，`然後~`蜂擁~`入~`城~，`直~`奔~`府衙~`門~。」"],"s":"`蜂湧~,`簇擁~"}],"p":"fēng yǒng"}],"t":"`蜂~`擁~","translation":{"Deutsch":["in Schwärmen kommen, wimmeln  (V)"],"English":["to flock (to see)","to mill","to throng"],"francais":["se presser en foule désordonnée","se ruer","se presser en foule"]}}