{"h":[{"b":"ㄅㄧㄠˇ　˙ㄗ","d":[{"f":"`女~`演員~。","q":["《`永樂大典~`戲文~`三~`種~．`宦門~`子弟~`錯~`立身~．`第一~`二~`出~》：「`被~`父母~`禁持~，`投東摸西~，`將~`一個~`表子~`依隨~。」"]},{"f":"`姘~`婦~。","q":["`元~．`李~`行道~《`灰~`闌~`記~．`第一~`折~》：「`你~`那裡~`是~`我~`搭識~`的~`表子~，`只當~`是~`我~`的~`娘~。」","《`水滸傳~．`第~`五~`一回~》：「`那~`知縣~`雖然~`愛~`朱~`仝~，`只是~`恨~`這~`雷~`橫~`打死~`了~`他~`表子~`白~`秀~`英~，`也~`容~`不得~`他說~`了~。」"]},{"f":"`妓女~。`元~．`石君寶~《`曲江池~．`第~`二~`折~》：「`也~`則~`俺~`一時間~`錯~`被~`鬼~`昏迷~，`是~`贍表子~`平生~`落得~`的~。」`清~．`孔尚任~《`桃花扇~．`第~`七~`齣~》：「`那些~`孤老~、`表子~，`還~`不知~`摟~`到~`幾時~`哩~！」`也~`作~「`婊子~」。"}],"p":"biǎo zi"}],"t":"`表~`子~"}