{"Deutsch":"zusammenzimmern ","English":"assembled at random","francais":"assemblé au hasard","h":[{"=":"352200000","b":"ㄑㄧ　ㄆㄧㄣ　ㄅㄚ　ㄘㄡˋ","d":[{"f":"`將~`零碎~`的~`東西~`勉強~`拼湊~`起來~。","q":["《`二十年目睹之怪現狀~．`第~`九~`二~`回~》：「`我~`才~`去~`對~`他說~`過~，`他~`也~`打~`了~`半天~`的~`算盤~；`說~`七拼八湊~，`還~`勉強~`湊~`得~`上來~；`三~`天~`之~`內~，`一定~`交~`到~。」"]},{"e":["`如~：「`這~`篇~`論文~`七拼八湊~，`了無新意~。」"],"f":"`隨便~`胡亂~`湊合~。"}],"p":"qī pīn bā còu"}],"t":"`七~`拼~`八~`湊~","translation":{"Deutsch":["zusammenzimmern "," etw. (behelfsmäßig) zusammenbasteln  (V)"],"English":["assembled at random","a motley collection"],"francais":["assemblé au hasard","drôle de collection"]}}