{"English":"Tripitaka (602-664) Tang dynasty Buddhist monk and translator, who traveled to India 629-645","h":[{"b":"ㄙㄢ　ㄗㄤˋ　ㄈㄚˇ　ㄕ","d":[{"f":"`精通~`佛教~`經~、`律~、`論~`三藏~`的~`比丘~。","l":["`簡稱~`為~「`三藏~」。"],"q":["`唐~．`志~`靜~〈`佛~`頂~`尊~`勝~`陀羅尼~`經~`序~〉：「`大帝~`遂~`將~`其~`本~`入~`內~，`請~`日照~`三藏法師~`及~`勅~`司~`賓~`寺~`典~`客~`令~`杜~`行~`顗~`等~`共~`譯~`此~`經~。」"]}],"p":"sān zàng fǎ shī"}],"t":"`三藏~`法師~","translation":{"English":["Tripitaka (602-664) Tang dynasty Buddhist monk and translator, who traveled to India 629-645","same as `玄奘~"]}}