{"English":"unclear","francais":"pas clair","h":[{"b":"ㄅㄨˋ　ㄑㄧㄥ","d":[{"f":"`汙濁~、`不~`淨~。","q":["《`楚辭~．`屈原~．`卜居~》：「`世~`溷濁~`而~`不清~，`蟬翼~`為~`重~，`千鈞~`為~`輕~。」","`晉~．`司馬~`彪~《`續漢書~．`卷~`五~．`黨錮~`傳~．`郭~`泰~`傳~》：「`叔~`度~`之~`器~，`汪汪~`若~`萬頃~`之~`波~，`澄~`之~`而~`不清~，`混~`之~`而~`不~`濁~，`不可~`量~`也~。」"]},{"e":["`如~：「`釋義~`不清~」、「`電視~`畫面~`不清~」。"],"f":"`模糊~`不清~`晰~。"},{"f":"`冗雜~`而~`無~`以~`了結~。","q":["《`紅樓夢~．`第~`六~○`回~》：「`趙~`姨娘~`便~`氣~`的~`瞪著眼~，`粗~`了~`筋~，`一五一十~，`說~`個~`不清~。」"]}],"p":"bù qīng"}],"t":"`不~`清~","translation":{"English":["unclear"],"francais":["pas clair"]}}