{"English":"low pressure","francais":"dépression (météorologie)","h":[{"=":"112700029","b":"ㄉㄧ　ㄑㄧˋ　ㄧㄚ","d":[{"e":["`如~：「`颱風~`屬於~`一~`種~`低氣壓~。」"],"f":"`大氣~`中氣~`壓~`較~`周圍~`低~`的~`地方~。`在~`低氣壓~`的~`上空~，`低~`層~`的~`空氣~`由~`四周~`向~`中心~`流動~，`所以~，`低氣壓~`地區~`的~`空氣~`有~`向上~`升~`的~`現象~，`這些~`上升~`的~`空氣~`到~`高處~`冷卻~`而~`凝結~，`形成~`雲~`和~`雨~，`故~`低氣壓~`區~`天氣~`較~`不穩~`定~。"},{"e":["`如~：「`自從~`股票市場~`不景氣~`之後~，`公司~`裡~`就~`籠罩~`在~`低氣壓~`之~`下~，`人心惶惶~。」"],"f":"`氣氛~`沉悶~`不穩~`定~。"}],"p":"dī qì yā"}],"t":"`低~`氣壓~","translation":{"English":["low pressure","depression (meteorology)"],"francais":["dépression (météorologie)"]}}