{"Deutsch":" Art und Weise etw. künstlerisch darzustellen  (S, Kunst)","English":"course of action","francais":"procédé","h":[{"=":"539100011","b":"ㄗㄨㄛˋ　ㄈㄚˇ","d":[{"f":"`創立~`典章~、`法律~`等~。","q":["《`文選~．`干寶~．`晉~`紀~`總論~》：「`夫~`作法~`於~`治~，`其~`弊~`猶~`亂~；`作法~`於~`亂~，`誰~`能~`救~`之~。」"]},{"e":["`如~：「`這~`道~`菜~`的~`作法~`簡易~，`適合~`初學~`者~`學習~。」"],"f":"`製作~`的~`方法~。"},{"f":"`術~`者~`施行~`法術~。","q":["《`大唐三藏取經詩話~`上~》：「`然~`小行~`者~`被~`他~`作法~，`變作~`一個~`驢~`兒~，`吊~`在~`廳~`前~。」","《`三國演義~．`第~`二~`回~》：「`張~`寶~`作法~，`風雷~`大作~，`飛砂走石~，`黑~`氣~`漫天~，`滾滾~`人馬~，`自~`天~`而~`下~。」"]},{"f":"`作文章~`的~`方法~。","q":["《`紅樓夢~．`第~`四~`八~`回~》：「`香~`菱~`笑~`道~：『`好~`姑娘~，`別~`混~`我~。』`一面~`說~，`一面~`作~`了~`一~`首~，`先~`與~`寶釵~`看~。`寶釵~`看~`了~，`笑~`道~：『`這個~`不好~，`不是~`這個~`作法~。』」"]},{"f":"`做~`懲戒~`的~`榜樣~。","q":["《`紅樓夢~．`第~`九~`回~》：「`今~`見~`秦~`香~`二~`人~`來~`告~`金~`榮~，`賈~`瑞~`心中~`便~`更~`不自在~`起來~，`雖~`不好~`呵叱~`秦~`鐘~，`卻~`拿~`著~`香~`憐~`作法~，`反~`說~`他~`多事~，`著實~`的~`搶白~`了~`幾~`句~。」"]}],"p":"zuò fǎ"}],"t":"`作~`法~","translation":{"Deutsch":[" Art und Weise etw. künstlerisch darzustellen  (S, Kunst)","Ausführung, Ausführungsweise, Ausführungsart  (S)","Kompositionsweise, Art und Weise etw. zu komponieren  (S, Mus)","Schreibweise, Schreibstil  (S, Lit)","Art und Weise etw. zu praktizieren bzw. ausüben  (V)","Gesetze beschließen, schaffen, verfassen  (V, Rechtsw)","magische Rituale ausführen  (V, Gesch)"],"English":["course of action","method of doing sth","practice","modus operandi"],"francais":["procédé","pratique"]}}