{"Deutsch":"exzentrisch, außermittig, außer Mitte  (Adj)","English":"partial","francais":"partialité","h":[{"b":"ㄆㄧㄢ　ㄒㄧㄣ","d":[{"f":"`偏袒~`一方~，`對~`某~`一方~`存~`私心~。","q":["《`西遊記~．`第一~`四~`回~》：「`我們~`這~`一~`國君~`王~，`偏心~`無道~，`只~`喜得~`是~`老爺~`等~`輩~，`惱~`的是~`我們~`佛子~。」","《`紅樓夢~．`第~`七~`一回~》：「`前兒~`你~`姊妹~`們~`和~`寶玉~`都~`揀~`了~，`如今~`也~`叫~`你們~`揀~`揀~，`別說~`我~`偏心~。」"]}],"p":"piān xīn"}],"t":"`偏~`心~","translation":{"Deutsch":["exzentrisch, außermittig, außer Mitte  (Adj)"],"English":["partial","biased","prejudiced","eccentric"],"francais":["partialité"]}}