{"English":"advance party","francais":"détachement précurseur","h":[{"b":"ㄒㄧㄢ　ㄑㄧㄢˇ　ㄉㄨㄟˋ","d":[{"e":["`如~：「`我們~`決定~`派~`老~`王~`擔任~`先遣隊~，`去~`那~`家~`新~`開~`的~`麵店~`試~`吃~。」"],"f":"`原~`指~`在~`軍隊~`之前~`負責~`聯絡~、`偵察~`等~`任務~`的~`部隊~。`後~`泛指~`在行~`動~`前~`所~`派~`出~`擔任~`聯繫~、`查~`探~`等~`工作~`的~`人~。"}],"p":"xiān qiǎn duì"}],"t":"`先~`遣~`隊~","translation":{"English":["advance party","advance troops"],"francais":["détachement précurseur","élément précurseur","échelon précurseur","groupe de reconnaissance","mission préparatoire"]}}