{"English":"internal trouble and outside aggression (idiom); in a mess both domestically and abroad","francais":"troubles intérieurs et danger d'invasion étrangère","h":[{"=":"160400066","b":"ㄋㄟˋ　ㄧㄡ　ㄨㄞˋ　ㄏㄨㄢˋ","d":[{"f":"`語~`本~《`管子~．`戒~》：「`君~`外舍~`而~`不~`鼎~`饋~，`非~`有~`內憂~，`必~`有~`外患~。」`指~`國家~`內部~`的~`動亂~`和~`外敵~`的~`侵擾~。《`孽~`海~`花~．`第~`二~`五~`回~》：「`當此~`內憂外患~，`接踵而來~，`老夫子~`繫~`天下人~`望~。」`亦~`比喻~`個人~`所~`遭遇~`的~`內在~`糾紛~`與~`外在~`壓力~`的~`困境~。`清~．`方苞~〈`兄~`子~`道~`希~`墓誌銘~〉：「`時~`弟妹~`皆~`幼~，`內憂外患~，`獨身~`當~`亡~，`遂~`得~`危~`疾~，`連年~`景~`歲~。」"}],"p":"nèi yōu wài huàn"}],"t":"`內憂~`外患~","translation":{"English":["internal trouble and outside aggression (idiom); in a mess both domestically and abroad"],"francais":["troubles intérieurs et danger d'invasion étrangère","guerre civile et péril venant du dehors"]}}