{"English":"lit. to ruin the enterprise for the sake of one basketful","francais":"(expr. idiom.) échouer à un doigt du succès","h":[{"=":"246700013","b":"ㄍㄨㄥ　ㄎㄨㄟ　ㄧ　ㄎㄨㄟˋ","d":[{"a":"`堅持不懈~,`善始善終~","f":"`堆~`一座~`九~`仞~`高~`的~`土山~，`因~`差~`最後~`一~`筐~`而~`不能~`成功~。`語~`出~《`書經~．`旅~`獒~》：「`為山九仞，功虧一簣~。」`比喻~`事情~`不能~`堅持到底~，`只~`差~`最後~`的~`步驟~`而~`功敗垂成~。《`晉書~．`卷~`五~`九~．`汝~`南~`王~`亮~`等~`傳~．`贊~`曰~》：「`長~`沙~`奉~`國~，`始終~`靡~`慝~；`功虧一簣~，`奄~`罹~`殘賊~。」","s":"`半途而廢~,`功敗垂成~,`前功盡棄~"}],"p":"gōng kuī yī kuì"}],"t":"`功~`虧~`一~`簣~","translation":{"English":["lit. to ruin the enterprise for the sake of one basketful","to fail through lack of a final effort","to spoil the ship for a ha'penny worth of tar (idiom)"],"francais":["(expr. idiom.) échouer à un doigt du succès","faire naufrage au port"]}}