{"Deutsch":"heißen  (V)","English":"to shout","c":5,"h":[{"=":"3222","b":"ㄐㄧㄠˋ","d":[{"e":["`如~：「`大呼小叫~」、「`拍手叫好~」、「`吼叫~」、「`鬼~`叫~」。"],"f":"`呼喊~。","q":["《`詩經~．`小雅~．`北山~》：「`或~`不知~`叫號~，`或~`慘慘~`劬勞~。」"],"type":"`動~"},{"e":["`如~：「`雞~`叫~」、「`鳥~`叫~」、「`貓~`叫~」。"],"f":"`鳴~。","type":"`動~"},{"e":["`如~：「`你~`叫~`什麼~`名字~？」、「`杜鵑~`鳥~`也~`叫子~`規~。」"],"f":"`稱~`做~、`稱~`為~。","q":["《`警世通言~．`卷~`一~`八~．`老~`門生~`三世~`報恩~》：「`這等~`看~`將~`起來~，`那~`八~`十~`歲~`上~`還是~`他~`初~`束髮~，`剛~`頂~`冠~，`做~`新郎~，`應~`童子試~`的~`時候~，`叫~`不得~`老年~。」"],"type":"`動~"},{"e":["`如~：「`叫~`他~`明天~`來~！」、「`先生~`叫~`你~。」"],"f":"`召喚~、`呼喚~，`多~`含~`命令~`口氣~。","type":"`動~"},{"e":["`如~：「`叫車~」、「`叫菜~」。"],"f":"`僱用~、`點~`購~。","type":"`動~"},{"e":["`如~：「`他~`天天~`咬耳朵~`傳話~，`真~`叫~`人~`討厭~！」"],"f":"`使~、`讓~、`令~。","type":"`動~"},{"e":["`如~：「`他~`的~`文章~`叫~`人~`批評~`得~`體無完膚~。」"],"f":"`被~、`受~。","type":"`介~"}],"p":"jiào"}],"n":2,"r":"`口~","t":"叫","translation":{"Deutsch":["heißen  (V)","rufen  (V)"],"English":["to shout","to call","to order","to ask","to be called","by (indicates agent in the passive mood)"]}}