{"Deutsch":"Unruhe stiften  (Sprichw)","English":"to call the wind and summon the rain (idiom); to exercise magical powers","francais":"(expr. idiom.) appeler le vent et convoquer la pluie","h":[{"=":"280300001","b":"ㄏㄨ　ㄈㄥ　ㄏㄨㄢˋ　ㄩˇ","d":[{"f":"`比喻~`神仙~`道士~`有~`颳風~`下雨~`的~`法術~。","q":["《`三國演義~．`第一~`回~》：「`角~`得~`此~`書~，`曉~`夜~`攻習~，`能~`呼~  `風~`喚雨~，`號~`為~『`太平道~`人~』。」","《`西遊記~．`第~`四~`四~`回~》：「`我~`那~`師父~，`呼風喚雨~，`只在~`翻掌~`之~`間~；`指~`水~`為~`油~，`點石成金~，`卻~`如~`轉身~`之~`易~。」"]},{"e":["`如~：「`他~`在~`商業~`界~`呼風喚雨~`的~`能力~，`叫~`人~`不得不~`佩服~。」"],"f":"`比喻~`人~`的~`神通廣大~、`影響力~`大~。"}],"p":"hū fēng huàn yǔ"}],"t":"`呼~`風~`喚雨~","translation":{"Deutsch":["Unruhe stiften  (Sprichw)"],"English":["to call the wind and summon the rain (idiom); to exercise magical powers","fig. to stir up troubles"],"francais":["(expr. idiom.) appeler le vent et convoquer la pluie","exercer des pouvoirs magiques","attiser les troubles"]}}