{"Deutsch":"Nai  (Eig, Fam)","English":"how can one help","c":8,"francais":"comment?","h":[{"=":"1600","b":"ㄋㄞˋ","d":[{"f":"`堪~、`經~`得~`起~。","l":["`通~「`耐~」。"],"q":["《`太平~`廣~`記~．`卷~`二~`三七~．`同~`昌~`公主~》：「`稍~`過度~，`則~`熇~`蒸~`之~`氣~`不可~`奈~。」"],"type":"`動~"},{"f":"`對付~、`安頓~、`處置~。`通常~`與~「`何~」`連用~。","q":["《`國語~．`晉~`語~`二~》：「`吾~`君~`老~`矣~，`國家~`多難~，`伯氏~`不出~，`奈~`吾~`君~`何~？」"],"type":"`動~"},{"e":["`如~：「`怎奈~`計畫~`不周~，`以致~`發生~`困難~。」、「`他~`本性~`不~`壞~，`無奈~`交友~`不慎~，`而~`誤入歧途~。」"],"f":"`表示~`意外~`轉折~`的~`語氣~。","type":"`連~"}],"p":"nài"}],"n":5,"r":"`大~","t":"奈","translation":{"Deutsch":["Nai  (Eig, Fam)","was, wie, aber (`无~`奈~ hilflos sein,  `怎奈~ aber) "],"English":["how can one help"],"francais":["comment?","moyen","ressource","(partic. disjonctive)"]}}