{"Deutsch":"den geeigneten Zeitpunkt feststellen und die Umstände richtig einschätzen ","English":"to judge the hour and size up the situation","francais":"prendre en considération le moment et la situation","h":[{"b":"ㄕㄣˇ　ㄕˊ　ㄉㄨㄛˋ　ㄕˋ","d":[{"f":"`詳細~`考量~`時局~`情勢~`的~`發展~`變化~。《`隋~`唐~`演義~．`第~`七八~`回~》：「`大凡~`士人~`出處~，`不可~`苟且~，`須~`審時度勢~，`必~`可以~`得~`行~`其~`志~，`方~`可~`一~`出~。」`也~`作~「`審時定勢~」。"}],"p":"shěn shí duò shì"}],"t":"`審~`時~`度~`勢~","translation":{"Deutsch":["den geeigneten Zeitpunkt feststellen und die Umstände richtig einschätzen "],"English":["to judge the hour and size up the situation","to take stock"],"francais":["prendre en considération le moment et la situation","tenir compte du moment et de la situation"]}}