{"English":"lit. your honored carriage","francais":"(lit.) votre calèche honorée","h":[{"b":"ㄗㄨㄣ　ㄐㄧㄚˋ","d":[{"f":"`駕~，`車駕~，`借~`指~`對方~。`尊駕~`為~`對對~`方~`的~`敬稱~。","q":["《`晉書~．`卷~`七~`一~．`王~`鑒~`傳~》：「`愚~`謂~`尊駕~`宜~`親~`幸~`江~`州~，`然後~`方~`召~`之~`臣~，`其~`力~`可~`得~`而~`宣~。」","《`儒林外史~．`第~`二~○`回~》：「`潘~`三~`哥~`在~`監~`裡~，`前日~`再三~`和~`我~`說~，`聽見~`尊駕~`回來~`了~，`意思~`要~`會一會~，`敘~`敘~`苦~`情~。」"],"s":"`大駕~,`閣下~"}],"p":"zūn jià"}],"t":"`尊~`駕~","translation":{"English":["lit. your honored carriage","your highness","honored Sir (also sarcastic)","you"],"francais":["(lit.) votre calèche honorée","votre grandeur","estimé monsieur (aussi sarcastique)","vous"]}}