{"Deutsch":"missmutig, unzufrieden ","English":"discontented","c":8,"francais":"aversion","h":[{"=":"6181","b":"ㄧㄤˋ","d":[{"f":"`不滿~、`不服氣~。","q":["《`說文解字~．`心~`部~》：「`怏~，`不服~`懟~`也~。」","《`戰國策~．`趙~`策~`三~》：「`辛~`垣~`衍~`怏然~`不悅~`曰~：『`嘻~！`亦~`太甚~`矣~`先生~`之~`言~`也~！』」"],"type":"`副~"},{"f":"`失意~、`惆悵~。","q":["《`廣韻~．`上聲~．`養~`韻~》：「`怏~，`怏~`悵~`也~。」"],"type":"`形~"},{"f":"`勉強~、`泥~`求~。","q":["`明~．`湯顯祖~《`牡丹亭~．`第~`二八~`齣~》：「`教~`俺~`迷留沒亂~`的~`心~`嘈雜~，`無~`夜~`無明~`怏~`著~`他~。」"],"type":"`動~"}],"p":"yàng"}],"n":5,"r":"`心~","t":"怏","translation":{"Deutsch":["missmutig, unzufrieden "],"English":["discontented"],"francais":["aversion","anxieux"]}}