{"Deutsch":"heulen, brüllen (Tiere), brüllen, Tierlaute ","English":"to bellow","francais":"rugir de colère","h":[{"=":"171400007","b":"ㄋㄨˋ　ㄏㄡˇ","d":[{"e":["`如~：「`狂風~`怒吼~」。"],"f":"`人~、`獸~`因~`憤怒~`而~`發出~`吼叫~。`也~`形容~`風~、`濤~`等~`發出~`巨大~`的~`聲音~。","q":["`清~．`紀昀~《`閱微草堂筆記~．`卷~`六~．`灤~`陽~`消夏~`錄~`六~》：「`于~`所~`蓄~`二~`牛~，`忽~`怒吼~`躍~`入~，`奮~`角~`與~`盜~鬪，`挺~`刃~`交~`下~，鬪`愈~`力~，`盜~`竟~`受傷~`狼狽~`去~。」"],"s":"`咆哮~"}],"p":"nù hǒu"}],"t":"`怒~`吼~","translation":{"Deutsch":["heulen, brüllen (Tiere), brüllen, Tierlaute "],"English":["to bellow","to rave","to snarl"],"francais":["rugir de colère"]}}