{"english":"Republic of Estonia","h":[{"b":"ㄞˋ　ㄕㄚ　ㄋㄧˊ　ㄧㄚˋ　ㄍㄨㄥˋ　ㄏㄜˊ　ㄍㄨㄛˊ","d":[{"f":"`國~`名~。`波羅的海三小國~`之~`一~。`位於~`歐洲~`北部~，`北~`瀕~`芬~`蘭~`灣~，`東~`界~`俄~`羅~`斯~，`南~`界~`拉~`脫~`維~`亞~，`西~`瀕~`波羅~`的~`海~，`面積~`四~`萬~`五~`千~`二~`百~`一~`十~`五~`平方公里~，`人口~`約~`一~`百~`五~`十~`八~`萬~。`首都~`為~`塔~`林~(Tallinn）。`語言~`以~`愛~`沙~`尼~`亞~`語~`為~`主~，`信仰~`新教~(Lutheran)。`本~`為~`一~`獨立~`共和國~，`於~`二~`次~`世界大戰~`期間~，`被~`前~`蘇聯~`併吞~，`成~`為~`其~`附庸國~`之~`一~。`西元~`一~`九九~○`年~`起~，`與其~`他~`二~`小~`國~`致力~`於~`脫離~`前~`蘇聯~`的~`獨立~`工作~，`並~`廢除~`共~`黨~`專政~。`但~`直~`至~`一~`九九~`一~`年~`八~`月~`才~`趁~`前~`蘇聯~`政變~`之~`際~`宣布~`獨立~。`幣制~`為~`克~`朗~。","l":["`簡稱~`為~「`愛~`沙~`尼~`亞~」。"]}],"p":"ài shā ní yà gòng hé guó"}],"t":"`愛~`沙~`尼~`亞~`共和國~"}