{"English":"to feel suffocated or oppressed","francais":"suffoquer","h":[{"b":"ㄅㄧㄝ　ㄑㄧˋ","d":[{"e":["`如~：「`門窗~`關~`得~`緊緊~`的~，`真~`憋氣~。」"],"f":"`呼吸~`受阻~`礙~`而~`不順~`暢~。"},{"e":["`如~：「`要~`學習~`游泳~，`得~`先~`學~`憋氣~。」"],"f":"`將~`氣~`憋~`住~，`不~`使~`它~`呼~`出~。"},{"f":"`心中~`受委屈~`或有~`煩惱~`無法~`解決~`宣洩~。","q":["《`劉知遠~`諸宮調~》`第~`二~：「`自~`入舍~`做~`女婿~，`覷~`俺咱~`似~`兒戲~。`使~`著~`後~，`道東說西~`暢~`憋氣~。」"],"s":"`煩悶~"}],"p":"biē qì"}],"t":"`憋~`氣~","translation":{"English":["to feel suffocated or oppressed","to choke with resentment","to feel injured or resentful"],"francais":["suffoquer"]}}