{"English":"composed, contented","c":15,"h":[{"b":"ㄒㄧㄢˊ","d":[{"f":"`閒適~`自得~。","q":["`唐~．`柳宗元~〈`酬~`韶~`州~`裴~`曹~`長~`使君~`寄~`道~`州~`呂~`八~`大使~`因~`以~`見示~`二~`十~`韻~〉：「`循~`省~`誠~`知~`懼~，`安排~`祗~`自~`憪~。」"],"type":"`形~"}],"p":"xián"},{"b":"ㄒㄧㄢˋ","d":[{"f":"`不安~。","q":["《`史記~．`卷~`一~○．`孝~`文~`本紀~》：「`朕~`既~`不能~`遠~`德~，`故~`憪~`然~`念~`外人~`之~`有~`非~。」","《`聊齋志異~．`卷~`四~．`羅剎~`海~`市~》：「`馬~`至~`是~`孤立~，`憪~`然~`不~`自~`安~。」"],"type":"`副~"},{"f":"`忿怒~`的~`樣子~。","q":["《`新唐書~．`卷~`一~`六~`八~．`王~`叔~`文~`傳~》：「`憪~`然~`謂~`天下~`無~`人~。」"],"type":"`副~"}],"p":"xiàn"}],"n":12,"r":"`心~","t":"憪","translation":{"English":["composed, contented"]}}