{"Deutsch":"abwehren  (V)","English":"to resist","francais":"tenir bon","h":[{"=":"435000015","b":"ㄓㄠ　ㄐㄧㄚˋ","d":[{"f":"`正面~`接下~`挑戰~。","q":["《`喻世明言~．`卷~`六~．`葛~`令公~`生~`遣~`弄~`珠~`兒~》：「`一連~`四~`五~`日~`挑戰~，`李~`存~`璋~`牢~`守~`寨柵~，`只~`不招~`架~。」"]},{"a":"`投降~,`屈服~","f":"`抵擋~、`接招~。","q":["`清~．`洪昇~《`長生殿~．`第一~`五~`齣~》：「`拚~`受~`打和~`罵~，`將身~`去~`招架~！`將身~`去~`招架~！」"],"s":"`反抗~,`抵擋~,`抵抗~"},{"f":"`招呼~`款待~。","q":["《`警世通言~．`卷~`一~`七~．`鈍~`秀才~`一朝~`交泰~》：「`曹~`公~`見~`其~`衣衫不整~，`心下~`不悅~，`又~`知~`是~`王~`振~`的~`仇家~，`不敢~`招架~，`送~`下~`小小~`程儀~，`就~`辭~`了~。」","《`醒世恆言~．`卷~`二~○．`張~`廷~`秀~`逃生~`救~`父~》：「`張~`權~`瞧見~，`便~`放下~`手~`中~`生活~，`上前~`招架~`道~：『`員外~`要~`甚~`家火~？`裡面~`請~`看~。』」"]},{"f":"`招認~、`承認~。","q":["《`西遊記~．`第~`八~`六~`回~》：「`汝~`等~`見~`他~，`須要~`行~`個~`大禮~，`叫~`他~`聲~『`孫~`老爺~』，`他~`就~`招架~`了~。」","《`警世通言~．`卷~`七~．`陳~`可~`常~`端陽~`仙~`化~》：「`他~`若~`欺心~`不招~`架~`時~，`左右~`做我不著~，`你~`兩~`個~`老人家~`將~`我~`去~`府~`中~，`等~`我~`郡王~`面前~`實~`訴~。」"]}],"p":"zhāo jià"}],"t":"`招~`架~","translation":{"Deutsch":["abwehren  (V)"],"English":["to resist","to ward off","to hold one's own","to receive guests"],"francais":["tenir bon","résister à","se défendere"]}}