{"Deutsch":"ziehen  (V)","English":"to draw out","c":12,"francais":"tirer","h":[{"=":"6453","b":"ㄩˊ","d":[{"f":"`拖曳~、`牽引~。","q":["《`說文解字~．`手~`部~》：「`揄~，`引~`也~。」","《`史記~．`卷~`一一~`七~．`司馬相如~`傳~》：「`於是~`鄭~`女~`曼~`姬~，`被~`阿~`錫~，`揄~`紵~`縞~。」","`唐~．`張~`守節~．`正義~：「`揄~，`曳~`也~。」","《`聊齋志異~．`卷~`一~．`嬌娜~》：「`女~`乃~`斂~`羞~`容~，`揄~`長~`袖~，`就~`榻~`診視~。」"],"type":"`動~"},{"f":"`揮動~。","q":["《`韓非子~．`內~`儲~`說~`下~》：「`御者~`因~`揄~`刀~`而~`劓~`美人~。」","《`淮南子~．`氾~`論~》：「`揄~`三尺~`之~`刃~，`造~`桓~`公~`之~`胸~。」"],"type":"`動~"},{"f":"`引~`出~、`提出~。","q":["《`淮南子~．`主~`術~》：「`使~`言~`之~`而~`非~`也~，`雖~`在~`卿~`相人~`君~，`揄~`策~`於~`廟堂~`之~`上~，`未必~`可~`用~。」","《`漢書~．`卷~`二~`二~．`禮樂~`志~》：「`神~`之~`揄~，`臨~`壇宇~。」","`唐~．`顏師古~．`注~：「`言~`神~`引~`來~`降臨~`之~`也~。」"],"type":"`動~"},{"f":"`參見~「`揶揄~」`條~。","type":"`動~"}],"p":"yú"},{"b":"ㄧㄡˊ","d":[{"f":"`清理~`米~`臼~，`取~`出~`米~`臼~`中的~`米~。","q":["《`詩經~．`大雅~．`生民~》：「`或~`舂~`或~`揄~，`或~`簸~`或~`蹂~。」","`漢~．`鄭玄~．`箋~：「`揄~，`抒~`臼~`也~。」"],"type":"`動~"}],"p":"yóu"},{"b":"ㄧㄠˊ","d":[{"f":"`參見~「`揄狄~」`條~。"}],"p":"yáo"}],"n":9,"r":"`手~","t":"揄","translation":{"Deutsch":["ziehen  (V)","aufheben, hochheben "],"English":["to draw out","to let hanging"],"francais":["tirer","élever"]}}