{"English":"to launder clothes by pounding","h":[{"b":"ㄉㄠˇ　ㄧ","d":[{"f":"`用~`杵~`捶打~`生絲~`以~`去~`蠟~，`使~`生絲~`柔~`白~`而~`富有~`彈性~，`而~`能~`裁成~`衣物~。`也~`作~「`搗~`練~」、「`擣衣~」。"},{"f":"`以~`杵~`捶~`擊~`衣物~`使~`乾淨~。`北周~．`庾信~〈`夜~`聽~`搗衣~〉`詩~：「`秋~`夜~`搗衣~`聲~，`飛~`度~`長門~`城~。」《`老殘遊記~．`第~`三~`回~》：「`走~`著~`看~`著~，`見~`河岸~`南面~`有~`幾個~`大~`長方~`池子~，`許多~`婦女~`坐~`在~`池~`邊~`石~ `上~`搗衣~。」`也~`作~「`擣衣~」。"},{"f":"`樂曲~`名~。`為~`琴~`曲~。`相傳~`為~`唐~`代~`潘~`庭~`堅~`所~`作~。`古代~`秋涼~`時~，`家家~`婦女~`為~`親人~`趕~`冬衣~`而~`搗衣~，`故~`樂曲~`以~`表現~`婦女~`對~`遠方~`親人~`思念~`的~`情感~`為~`主~。`或~`稱~`為~〈`搗衣~`曲~〉、〈`秋~`杵~`弄~〉、〈`秋水~`弄~〉、〈`秋~`院~`搗衣~〉。"}],"p":"dǎo yī"}],"t":"`搗~`衣~","translation":{"English":["to launder clothes by pounding"]}}