{"Deutsch":"groß essen gehen, ein Festgelage veranstalten  (V)","English":"to pick up (a powder etc) with the fingertips","c":15,"francais":"prendre avec les doigts","h":[{"b":"ㄘㄨㄛ","d":[{"f":"`抓~`取~。","q":["《`莊子~．`秋水~》：「`鴟鵂~`夜~`撮~`蚤~，`察~`毫末~，`晝~`出~`瞋目~`而~`不見~`丘山~，`言~`殊~`性~`也~。」","《`儒林外史~．`第~`二~`回~》：「`撮~`了~`一把~`苦~`丁~`茶葉~。」"],"type":"`動~"},{"f":"`聚攏~。","q":["《`孔子家語~．`卷~`一~．`始~`誅~》：「`其~`聚~`處~`足以~`撮~`徒~`成~`黨~，`其~`談~`說~`足以~`飾~`褒~`榮~`眾~。」"],"type":"`動~"},{"f":"`摘錄~。","q":["《`史記~．`卷~`一~`三~○．`太史公~`自序~》：「`采~`儒~、`墨~`之~`善~，`撮~`名~、`法~`之~`要~。」","《`紅樓夢~．`第~`四~`二~`回~》：「`將~`市俗~`的~`粗話~，`撮~`其~`要~，`刪~`其~`繁~，`再~`加~`潤色~`比方~`出來~。」"],"type":"`動~"},{"f":"`量詞~：(1) `計算~`容量~`的~`單位~。`公制~`一~`撮~`等於~`千~`分~`之~`一~`升~。`也~`稱~`為~「`公撮~」。(2) `計算~`手指~`抓~`取~`物~`的~`單位~。`如~：「`一~`撮~`鹽~」、「`一~`撮土~」。","type":"`名~"}],"p":"cuō"},{"b":"ㄗㄨㄛˊ","d":[{"f":"`牽引~。","q":["《`集韻~．`入聲~．`末~`韻~》：「`撮~，`挽~`也~。」"],"type":"`動~"}],"p":"zuó"},{"=":"5516","b":"（`又~`音~）ㄘㄨㄛˋ","d":[{"f":"(`一~)`之~`又~`音~。"}],"p":"（`又~`音~）cuò"},{"b":"ㄗㄨㄟˋ","d":[{"f":"`參見~「`會撮~」`條~。"}],"p":"zuì"},{"b":"ㄗㄨㄛˇ","d":[{"e":["`如~：「`一~`撮~`頭髮~」。"],"f":"`量詞~。`計算~`成~`叢~`的~`毛髮~`或~`野草~`等~`的~`單位~。","type":"`名~"}],"p":"zuǒ"}],"n":12,"r":"`手~","t":"撮","translation":{"Deutsch":["groß essen gehen, ein Festgelage veranstalten  (V)"],"English":["to pick up (a powder etc) with the fingertips","to scoop up","to collect together","to extract","to gather up","classifier: pinch","Taiwan pr. [cuo4]","classifier for hair or grass: tuft","Taiwan pr. [cuo4]"],"francais":["prendre avec les doigts","une pincée","choisir","ramasser"]}}