{"Deutsch":"Überfüllung  (S)","English":"to be clogged up","francais":"embouteillage (voiture, foule etc..)","h":[{"b":"ㄩㄥˇ　ㄙㄜˋ","d":[{"f":"`阻塞~。《`晏子春秋~．`內~`篇~．`諫~`上~》：「`忠臣~`擁塞~，`諫言~`不出~。」《`儒林外史~．`第一~`四~`回~》：「`只見~`左邊~`一~`條~`小徑~，`莽榛蔓草~，`兩邊~`擁塞~。」`也~`作~「`壅塞~」。"}],"p":"yǒng sè"}],"t":"`擁~`塞~","translation":{"Deutsch":["Überfüllung  (S)","Überlastung  (S)","Stau  (S)"],"English":["to be clogged up","to be congested (traffic, computer network etc)"],"francais":["embouteillage (voiture, foule etc..)","bouchons","bloquer"]}}