{"Deutsch":" verehren  (S, Philos)","English":"to worship piously","francais":"vénérer","h":[{"=":"340600003","b":"ㄐㄧㄥˋ　ㄈㄥˋ","d":[{"f":"`恭敬~`的~`遵從~`與~`奉行~。","q":["《`左傳~．`宣~`公~`十~`五~`年~》：「`後~`之~`人~`或者~`將~`敬奉~`德~`義~，`以~`事~`神人~，`而~`申~`固~`其~`命~。」"]},{"f":"`以~`物~`贈~`人~`的~`敬辭~。","q":["`宋~．`陸游~〈`戒~`殺~〉`詩~：「`豈~`無~`園~`中~`蔬~，`敬奉~`君子~`宴~。」"]},{"e":["`如~：「`敬奉~`指示~」。"],"f":"`表示~`接~`到~`長輩~`的信~`或~`上級~`公文~`的~`敬~`語~。"}],"p":"jìng fèng"}],"t":"`敬~`奉~","translation":{"Deutsch":[" verehren  (S, Philos)"],"English":["to worship piously","to present","to dedicate"],"francais":["vénérer","offrir respectueusement"]}}