{"Deutsch":"Richtung, Orientierung  (S)","English":"direction","francais":"direction","h":[{"=":"089200007","b":"ㄈㄤ　ㄒㄧㄤˋ","d":[{"f":"`東南~`西北~`上下~`等~`區別~。","q":["《`紅樓夢~．`第~`三~`九~`回~》：「`按~`著~`劉~`姥姥~`說~`的~`方向~`地~`名~，`著~`茗~`煙~`去~`先~`踏看~`明白~，`回來~`再~`做主~`意~。」"]},{"e":["`如~：「`朝~`目標~`方向~`前進~。」"],"f":"`面對~`的~`方位~。","s":"`目標~"}],"p":"fāng xiàng"},{"=":"089200008","b":"ㄈㄤ　˙ㄒㄧㄤ","d":[{"e":["`如~：「`看~`方向~`做事~。」"],"f":"`情勢~。"}],"p":"fāng xiang"}],"t":"`方~`向~","translation":{"Deutsch":["Richtung, Orientierung  (S)"],"English":["direction","orientation","path to follow","CL:`個~|`个~[ge4]"],"francais":["direction","orientation"]}}