{"Deutsch":"etw. genau wissen  (V)","English":"to be fully aware of","francais":"être pleinement conscient de","h":[{"b":"ㄇㄧㄥˊ　ㄓ","d":[{"f":"`清楚~`的知~`道~。","q":["《`文選~．`枚乘~．`上書~`重~`諫~`吳~`王~》：「`此~`其~`與~`秦~`地~`相~`什~`而~`民~`相~`百~，`大王~`之~`所~`明知~`也~。」","《`紅樓夢~．`第~`六~`一回~》：「`我~`心裡~`明知~`不是~`他~`偷~`的~，`可憐~`他~`害怕~`都~`承認~`了~。」"]}],"p":"míng zhī"}],"t":"`明~`知~","translation":{"Deutsch":["etw. genau wissen  (V)"],"English":["to be fully aware of","to know perfectly well"],"francais":["être pleinement conscient de","savoir parfaitement"]}}