{"English":"to worship","francais":"faire un pèlerinage","h":[{"=":"468800001","b":"ㄔㄠˊ　ㄅㄞˋ","d":[{"f":"`祭拜~`祖先~`或~`神~、`佛~。","q":["`南朝~`梁~．`陶弘景~〈`授~`陸~`敬~`游~`十~`賚~`文~〉：「`今~`故~`賚~`爾~`鍮石~`澡~`灌~，`手巾~`為~`副~，`可以~`登~`齋~`朝拜~，`出入~`盥漱~。」"]},{"f":"`君主~`時代~`官員~`對~`皇帝~`的~`覲見~`跪拜~。","q":["《`儒林外史~．`第~`三五~`回~》：「`莊~`徵~`君~`戴~`了~`朝巾~，`穿~`了~`公服~，`跟~`在~`班~`末~，`嵩呼~`舞蹈~，`朝拜~`了~`天子~。」"]},{"f":"`拜謁~、`求見~。","q":["《`西遊記~．`第~`五七~`回~》：「`木~`叉~`情知~`是~`尋~`行者~，`更~`不題~`起~，`即~`先進~`去~`對~`菩薩~`道~：『`外~`有~`唐~`僧~`的~`小~`徒弟~`沙悟淨~`朝拜~。』」"]}],"p":"cháo bài"}],"t":"`朝~`拜~","translation":{"English":["to worship","to make customary deferences to","a pilgrimage"],"francais":["faire un pèlerinage","présenter ses respects à un souverain"]}}