{"Deutsch":"ziemlich, ein bisschen zu...  (Adj)","English":"unavoidably","francais":"plutôt","h":[{"=":"633700006","b":"ㄨㄟˋ　ㄇㄧㄢˇ","d":[{"f":"`未必~`沒有~，`表~`必然~`的~`語氣~。","q":["《`老殘遊記~．`第一~`八~`回~》：「`老哥~`連~`他~`都~`當做~`小人~，`所以~`我~`說~`未免~`過分~`了~。」","《`文明~`小史~．`第~`四~○`回~》：「`說~`那裡~`話~？`未免~`太~`把~`內人~`輕~`看~`了~。」"],"s":"`不免~  2.`難免~"},{"f":"`免不得~。","q":["《`五代史~`平話~．`梁~`史~．`卷~`上~》：「`那時~`分~`又是~`秋~`來~`天氣~，`黃巢~`愁悶~`中~`未免~`題~`了~`一~`首~`詩~。」","《`紅樓夢~．`第一~`七~、`一~`八~`回~》：「`固然~`係~`人力~`穿鑿~，`此時~`一~`見~，`未免~`勾引~`起~`我~`歸農~`之~`意~。」"]}],"p":"wèi miǎn"}],"t":"`未~`免~","translation":{"Deutsch":["ziemlich, ein bisschen zu...  (Adj)"],"English":["unavoidably","can't help","really","rather"],"francais":["plutôt","peut-être"]}}