{"Deutsch":"Kiefer  (S)","English":"China fir","c":7,"francais":"sapin de Chine","h":[{"=":"5017","b":"（`讀音~）ㄕㄢ","d":[{"f":"`植物~`名~。`杉~`科~`杉木~`屬~，`常~`綠~`喬木~。`樹幹~`端~`直~，`高~`數~`丈~，`樹皮~`縱~`裂~。`葉~`線~`狀~`針~`形~，`螺旋狀~`著~`生~。`單性花~，`秋天~`結~`卵~`圓形~`毬果~。`木材~`可~`供~`建築~`和~`製造~`器具~`用~，`用途~`甚~`廣~。`多~`栽培~`在~`八~`百~`公尺~`到~`一~`千~`八~`百~`公尺~`高~`的~`山地~。","type":"`名~"}],"p":"（`讀音~）shān"},{"b":"（`語音~）ㄕㄚ","d":[{"f":"(`一~)`之~`語音~。"}],"p":"（`語音~）shā"}],"n":3,"r":"`木~","t":"杉","translation":{"Deutsch":["Kiefer  (S)","Tanne  (S)","Zeder  (S)","Kiefer  (S)","Tanne, Fichte  (S)","Zeder  (S)"],"English":["China fir","Cunninghamia lanceolata","also pr. [sha1]"],"francais":["sapin de Chine","Cunninghamia lanceolata"]}}