{"h":[{"b":"ㄘˋ　ㄨㄟˊ　ㄇㄧˇ　ㄐㄧˋ　ㄏㄨㄚˋ","d":[{"f":"`次~`微米~`指~`小~`於~`一~`微米~`的~`半導體~`製作~`技術~。`民國~`七~`十~`九~`年~，`政府~`為~`建立~`完整~`之~`半導體~`產業~，`期盼~`能~`引導~`產業~`進入~`次~`微米~`時代~。`乃~`由~`經濟部~`委託~`工研院~`電子~`所~`主導~，`並~`撥~`列~`經費~`以~`規劃~`籌建~`次~`微米~`實驗室~，`做~`為~`驅動~`我國~IC`技術~`跨~`入~`次~`微米~`新紀元~`的~`前哨~。`七~`十~`九~`年~`七月~，`次微米計畫~`研發~`工作~`正式~`展開~，`為期~`五~`年~（`西元~`一~`九九~○`至~`一~`九九~`五~`年~）。`整體~`計畫~`目標~`如~`下~：(1) `建立~`一座~`八~`吋~`晶~`圓~，Class 0.1 (0.3`微米~）`的~`世界~`一流~`水準~`的~`實驗室~，`以~`提供~`開發~`次~`微米~`製~`程~`技術~。(2) `在~`一~`九九~`五~`年~`以前~`使~`中華~`民國~`具備~：a. 0.7/0.5`微米~`整合~`製~`程~`技術~。b. 0.35 `微米~`製~`程~`模組~`技術~。(3) `建立~`超~`潔淨~`技術~`及~`八~`吋~`晶~`圓~`量產~`型~`技術~。(4) `建立~`中華~`民國~`極~`大型積體電路~（ULSI）`研究~`發展~`能力~，`並~`對~`世界~IC`研究~`發展~`的~`領域~`有~`所~`貢獻~。"}],"p":"cì wéi mǐ jì huà"}],"t":"`次~`微米~`計畫~"}