{"Deutsch":"Stamm, Mutterpopulation  (S)","English":"(zoology, medicine) mother's body","francais":"corps de la mère","h":[{"b":"ㄇㄨˇ　ㄊㄧˇ","d":[{"e":["`如~：「`嬰兒~`未~`出生~`時~，`在~`母親~`腹~`中~，`以~`吸收~`母體~`的~`營養~`維生~。」"],"f":"`孕育~`幼兒~`的~`人~`或~`雌性~`動物~`的~`身體~。"},{"f":"`統計學~`上~`稱~`所~`欲~`探究~`之~`某~`種~`事物~`的~`全部~`範圍~。","l":["`也~`稱~`為~「`母~`群體~」。"]},{"f":"`泛指~`可~`分化~`出~`子~`體~`的~`本體~。"}],"p":"mǔ tǐ"}],"t":"`母~`體~","translation":{"Deutsch":["Stamm, Mutterpopulation  (S)"],"English":["(zoology, medicine) mother's body","(chemistry etc) parent","matrix","(statistics) population","parent population"],"francais":["corps de la mère","matrice"]}}