{"Deutsch":"an einem Vorteil teilhaben, etw. Gutes mitgenießen  (V)","English":"to bask in the light","francais":"tirer profit de ses relations","h":[{"=":"439100001","b":"ㄓㄢ　ㄍㄨㄤ","d":[{"f":"`帶~`有~`光澤~。","q":["`南朝~`宋~．`鮑照~〈`從~`登~`香爐峰~〉`詩~：「`羅~`景~`藹~`雲~`扃~，`沾光~`扈~`龍~`策~。」"]},{"f":"`有~`所~`連帶~`而~`享受~`到~`光彩~`與~`利益~。","q":["《`文明~`小史~．`第~`四~`四~`回~》：「`他說~`股本~`生財~`一概~`由~`他~`承認~，`他~`既然~`要~，`我們~`樂得~`多~`開~`些~，`大家~`多~`沾光~，`他~`兩~`個~`也~`不無小益~。」"],"s":"`叨光~"}],"p":"zhān guāng"}],"t":"`沾~`光~","translation":{"Deutsch":["an einem Vorteil teilhaben, etw. Gutes mitgenießen  (V)"],"English":["to bask in the light","fig. to benefit from association with sb or sth","reflected glory"],"francais":["tirer profit de ses relations"]}}