{"Deutsch":"Strömungslehre, Hydromechanik  (S, Phys)","English":"fluid mechanics","francais":"mécanique des fluides","h":[{"=":"196200014","b":"ㄌㄧㄡˊ　ㄊㄧˇ　ㄌㄧˋ　ㄒㄩㄝˊ","d":[{"f":"`研究~`作用~`在~`靜止~`或~`流動~`的~`氣體~、`液體~`各種~`力~`的~`科學~。`如~`流動~、`熱~`傳~、`壓縮~、`擴散~`及~`波動~`等~`性質~。`類別~`有~`流體~`靜~`力學~、`流體~`動力~`學~、`水力~`學~、`氣體~`力學~`等~。"}],"p":"liú tǐ lì xué"}],"t":"`流體~`力學~","translation":{"Deutsch":["Strömungslehre, Hydromechanik  (S, Phys)"],"English":["fluid mechanics","hydrodynamics"],"francais":["mécanique des fluides"]}}