{"Deutsch":"Heilkräutertee  (S)","English":"tisane","francais":"tisane","h":[{"=":"140400006","b":"ㄊㄤ　ㄧㄠˋ","d":[{"f":"`中醫~`指~`用水~`煎~`服~`的~`藥物~。","l":["`也~`稱~`為~「`湯劑~」。"],"q":["《`史記~．`卷~`一~○`一~．`袁盎~`鼂錯~`傳~》：「`陛下~`居~`代~`時~，`太后~`嘗~`病~，`三~`年~，`陛下~`不~`交睫~，`不解~`衣~，`湯藥~`非~`陛下~`口~`所~`嘗~`弗~`進~。」","《`文選~．`李密~．`陳情表~》：「`而~`劉~`夙~`嬰疾~`病~，`常在~`床蓐~，`臣~`侍~`湯藥~，`未曾~`廢~`離~。」"]}],"p":"tāng yào"}],"t":"`湯~`藥~","translation":{"Deutsch":["Heilkräutertee  (S)"],"English":["tisane","decoction (Chinese medicine)"],"francais":["tisane","décoction"]}}