{"Deutsch":"Morgentau, Manna, chinesische Artischocke ","francais":"Ganlou (53-50 av. J.-C.)","h":[{"=":"227800008","b":"ㄍㄢ　ㄌㄨˋ","d":[{"f":"`甘美~`的~`雨露~。`古人~`以為~`天下太平~`的~`瑞徵~。","q":["《`漢書~．`卷~`八~．`宣~`帝~`紀~》：「`乃者~`鳳~`皇~`集~`泰山~、`陳留~，`甘露~`降~`未央宮~。」","《`文選~．`賈誼~．`過~`秦~`論~》：「`甘露~`既~`降~，`朱~`草~`萌芽~。」"]},{"f":"`舊時~`迷信~`可以~`長生不老~`的~`仙~`水~。","q":["`元~．`關漢卿~《`竇娥冤~．`第~`二~`折~》：「`勝~`甘露~`灌~`體~，`得~`一個~`身子~`平安~`倒大來~`喜~。」"]},{"f":"`蚜蟲~`的~`分泌~`物~，`味~`甜~`如~`蜜~。"},{"f":"`年號~：(1) `漢朝~`宣~`帝~`年號~（`西元~`前~53～`前~50）。(2) `三國~`魏~`廢帝~`高貴~`鄉~`公~`年號~（`西元~  254～259)。(3) `三國~`吳~`主~`孫~`皓~`年號~（`西元~265～266)。(4) `前秦~`苻堅~`年號~（`西元~ 359  ～364）。"}],"p":"gān lù"}],"t":"`甘~`露~","translation":{"Deutsch":["Morgentau, Manna, chinesische Artischocke "],"francais":["Ganlou (53-50 av. J.-C.)"]}}