{"English":"lit. there are principles behind making money (idiom); fig. to have a knack for good business","h":[{"=":"5086000721","b":"ㄕㄥ　ㄘㄞˊ　ㄧㄡˇ　ㄉㄠˋ","d":[{"f":"`語~`本~《`禮記~．`大學~》：「`生財~`有~`大道~。」`形容~`擅長~`發財~`致富~。","q":["`元~．`錢~`霖~〈`哨~`遍~．`試~`把~`賢~`愚~`窮究~`套~．`五~`煞~〉：「`乾生受~，`生財有道~，`受用~`無由~。」"]}],"p":"shēng cái yǒu dào"}],"t":"`生財~`有道~","translation":{"English":["lit. there are principles behind making money (idiom); fig. to have a knack for good business","knowing how to accumulate wealth","good at feathering one's own nest"]}}