{"Deutsch":" jdn die Nacht bei sich auf nehmen  (V)","English":"to put up a guest","francais":"retenir un hôte pour la nuit","h":[{"=":"196500029","b":"ㄌㄧㄡˊ　ㄙㄨˋ","d":[{"f":"`留~`人~`住宿~。","q":["《`後漢書~．`卷~`一~`六~．`鄧~`寇~`列傳~．`鄧~`禹~》：「`禹~`曰~：『`但願~`明公~`威~`德~`加~`於~`四海~，`禹~`得~`效~`其~`尺寸~，`垂~`功名~`於~`竹帛~`耳~。』`光武~`笑~，`因~`留宿~`閒語~。」"],"s":"`止宿~,`住宿~"},{"f":"`停留~`下來~`住宿~`於~`此~。","q":["《`聊齋志異~．`卷~`四~．`狐~`諧~》：「`既~`不~`賜~`見~，`我輩~`留宿~，`宜~`勿~`去~，`阻~`其~`陽臺~。」"]}],"p":"liú sù"}],"t":"`留~`宿~","translation":{"Deutsch":[" jdn die Nacht bei sich auf nehmen  (V)","jmd Unterkunft anbieten  (V)"],"English":["to put up a guest","to stay overnight"],"francais":["retenir un hôte pour la nuit","rester pour passer la nuit"]}}