{"Deutsch":"ausbaggern ( Flußbett )  (V)","English":"to dredge","francais":"ouvrir un chemin","h":[{"=":"511000001","b":"ㄕㄨ　ㄉㄠˇ","d":[{"f":"`開通~`壅塞~`的~`河道~。","q":["《`宋史~．`卷~`二四~`九~．`王~`溥~`傳~》：「`疏導~`之~，`遂~`通~`舟楫~，`郡~`無~`水患~。」","《`三國演義~．`第~`八~○`回~》：「`大禹~`有~`疏導~`之~`績~，`而~`重華~`禪~`以~`帝位~。」"]},{"f":"`疏通~`勸導~。","q":["《`後漢書~．`卷~`四~．`孝~`和~`帝~`紀~》：「`刺史~、`二千石~`其~`隨宜~`疏導~。」"],"s":"`溝通~"}],"p":"shū dǎo"}],"t":"`疏~`導~","translation":{"Deutsch":["ausbaggern ( Flußbett )  (V)","ein Flußbett freiräumen  (V)","einen Kanal freigraben ( ausbaggern )  (V)","etw. klären, für Durchfluß sorgen  (V)"],"English":["to dredge","to open up a path for","to remove obstructions","to clear the way","to enlighten","persuasion"],"francais":["ouvrir un chemin","enlever les obstacles","éclairer","persuasion"]}}