{"Deutsch":"ermüden, Pneu  (S)","English":"to tire","francais":"fatigué","h":[{"b":"ㄆㄧˊ　ㄐㄩㄢˋ","d":[{"a":"`不倦~﹑`精神~","f":"`勞累~`困倦~。","q":["《`後漢書~．`卷~`一~`六~．`寇恂~`傳~》：「`今~`士~`馬~`疲倦~，`方~`履~`險阻~，`非~`萬乘~`之~`固~，`前年~`潁川~，`可~`為~`至~`戒~。」","《`五代史~`平話~．`晉~`史~．`卷~`上~》：「`皇帝~`跋涉~`遠~`來~，`士~`馬~`疲倦~，`卒~`與~`唐~`戰~`而~`大捷~，`何~`耶~？」"],"s":"`疲憊~﹑`疲乏~﹑`疲鈍~﹑`疲頓~﹑`疲勞~﹑`疲困~﹑`勞累~"}],"p":"pí juàn"}],"t":"`疲~`倦~","translation":{"Deutsch":["ermüden, Pneu  (S)","Mattigkeit  (S)","gelangweilt  (Adj)"],"English":["to tire","tired"],"francais":["fatigué","épuisé","las","lassé"]}}