{"Deutsch":"vermissen  (V)","English":"to miss","francais":"manquer (sentiment)","h":[{"=":"349700002","b":"ㄐㄩㄢˋ　ㄌㄧㄢˋ","d":[{"f":"`思戀~`愛慕~。","q":["`唐~．`孟浩然~〈`峴~`山~`送~`張~`去~`非~`游~`巴東~〉`詩~：「`蹉跎~`遊子~`意~，`眷戀~`故人~`心~。」","《`聊齋志異~．`卷~`一~○．`胭脂~》：「`生~`感~`其~`眷戀~`之~`情~，`愛慕~`殊~`切~。」"]},{"f":"`懷念~、`留戀~。","q":["《`紅樓夢~．`第~`六~`七~`回~》：「`柳~`湘~`蓮~`見~`尤~`三~`姐~`身亡~，`痴情~`眷戀~。」"]}],"p":"juàn liàn"}],"t":"`眷~`戀~","translation":{"Deutsch":["vermissen  (V)","verfehlen  (V)"],"English":["to miss","to long for","to remember with longing","yearning"],"francais":["manquer (sentiment)","se rappeler avec nostalgie","nostalgie","être attaché à","aimer","chérir"]}}