{"Deutsch":"berühmt  (Adj)","English":"well-known","francais":"connu","h":[{"=":"422600001","b":"ㄓ　ㄇㄧㄥˊ","d":[{"f":"`聲名~`很~`大~，`為人~`所知~。","q":["《`後漢書~．`卷~`五~`六~．`王~`龔~`傳~》：「`由是~`後進~`知名~`之~`士~，`莫不~`歸心~`焉~。」","`唐~．`李白~〈`讀~`諸葛~`武~`侯~`傳~`書~`懷~`贈~`長安~`崔~`少府~`叔~`封~`昆季~〉`詩~：「`毋~`令~`管~`與~`鮑~，`千載~`獨~`知名~。」"],"s":"`著名~"},{"f":"`聞~`知~`姓名~`或~`聲名~。","q":["`宋~．`梅~`堯~`臣~〈`雜~`詩~`絕句~〉`一~`七~`首~`之~`七~：「`岸~`傍~`草~`樹~`密~，`往往~`不知名~。」"]},{"f":"`告知~`姓名~。","q":["《`禮記~．`曲禮~`上~》：「`男女~`非~`有~`行媒~，`不相~`知名~。」"]}],"p":"zhī míng"}],"t":"`知~`名~","translation":{"Deutsch":["berühmt  (Adj)","prominent  (Adj)"],"English":["well-known","famous"],"francais":["connu","célèbre"]}}