{"Deutsch":"abändern, ändern  (V)","English":"to move","c":11,"francais":"déplacer","h":[{"=":"5863","b":"ㄧˊ","d":[{"e":["`如~：「`移植~」、「`遷移~」。"],"f":"`移轉~、`搬遷~。","q":["《`漢書~．`卷~`四~`九~．`鼂錯~`傳~》：「`美~`草~`甘水~`則~`止~，`草~`盡~`水~`竭~`則~`移~。」","`唐~．`李賀~〈`浩歌~〉：「`南風~`吹~`山~`作~`平地~，`帝~`遣~`天~`吳~`移~`海水~。」"],"type":"`動~"},{"e":["`如~：「`移風易俗~」、「`移孝作忠~」。"],"f":"`轉變~、`改變~。","q":["`唐~．`王勃~〈`滕王閣~〉`詩~：「`閒~`雲~`潭~`影~`日~`悠悠~，`物換星移~`幾~`度~`秋~？」"],"type":"`動~"},{"f":"`搖動~。","q":["《`禮記~．`玉藻~》：「`疾~`趨~`則~`欲~`發~，`而~`手足~`毋~`移~。」","`唐~．`孔穎達~．`正義~：「`移~`謂~`靡~`迆~`搖動~`也~。」"],"type":"`動~"},{"f":"`施予~、`贈送~。","q":["《`史記~．`卷~`一~○`四~．`田~`叔~`傳~》：「`鞅鞅~`如~`有~`移~`德~`於~`我~`者~，`何~`也~？」","《`漢書~．`卷~`八~`七~．`揚雄~`傳~`上~》：「`是以~`旃裘~`之~`王~，`胡~`貉~`之~`長~，`移~`珍~`來享~，`抗手~`稱臣~。」"],"type":"`動~"},{"f":"`去除~。","q":["`漢~．`王充~《`論衡~．`變~`虛~》：「`齊~`君~`欲~`禳~`慧~`星~`之~`凶~，`猶子~`韋~`欲~`移~`熒惑~`之~`禍~`也~。」"," `唐~．`柳宗元~〈`封建~`論~〉：「`削~`其~`半~，`民~`猶~`瘁~`矣~，`曷~`若~`舉~`而~`移~`之~，`以~`全~`其~`人~`乎~？」"],"type":"`動~"},{"f":"`一~`種~`官方~`文書~`的~`舊稱~，`行文~`於~`平行~`的~`對等~`單位~`之~`間~。","q":["《`後漢書~．`卷~`七~`四~．`袁紹~`傳~》：「`橋~`帽~`乃~`詐~`作~`三公~`移書~，`傳驛~`州郡~。」","《`新唐書~．`卷~`四六~．`百官~`志~`一~》：「`諸~`司~`相~`質~ `其~`制~`有~`三~：`一~`曰~`關~，`二~`曰~`制~，`三~`曰~`移~。」"],"type":"`名~"},{"f":"`姓~。`如~`漢~`代~`有~`移~`良~。","type":"`名~"}],"p":"yí"}],"n":6,"r":"`禾~","t":"移","translation":{"Deutsch":["abändern, ändern  (V)","austauschen, tauschen  (V)","entfernen, beseitigen  (V)","verschieben, verlegen, bewegen  (V)"],"English":["to move","to shift","to change","to alter","to remove"],"francais":["déplacer","mouvoir","supprimer","enlever","éliminer"]}}