{"English":"hole in a wall","c":14,"francais":"trou","h":[{"=":"6457","b":"ㄩˊ","d":[{"f":"`門~`邊~`牆~`上~`的~`圭~`形~`小~`洞~。","q":["《`說文解字~．`穴~`部~》「`窬~」`字~．`清~．`段~`玉~`裁~．`注~：「`是則~`於~`門~`旁~`穿~`壁~，`以~`木~`衺~`直~`居~`之~，`令~`如~`圭~`形~，`謂~`之~`圭窬~。」"],"type":"`名~"},{"f":"`挖~`鑿~、`穿鑿~。","q":["《`淮南子~．`泰~`族~》：「`埏埴~`而~`為~`器~，`窬木~`而~`為~`舟~。」"],"type":"`動~"},{"f":"`穿越~、`超越~。","l":["`通~「`踰~」。"],"q":["《`論語~．`陽~`貨~》：「`子~`曰~：『`色厲內荏~，`譬諸~`小人~，`其~`猶~`穿窬之盜~`也~`與~。』」"],"type":"`動~"}],"p":"yú"}],"n":9,"r":"`穴~","t":"窬","translation":{"English":["hole in a wall"],"francais":["trou","petite porte"]}}