{"Deutsch":"Kantonesisch, kantonesische Sprache (S, Sprachw)","English":"Cantonese language","francais":"cantonais (langue)","h":[{"b":"ㄩㄝˋ　ㄩˇ","d":[{"f":"`漢語~`方言~`之~`一~。`分布~`於~`廣東省~`中部~`和~`西南~`部~、`廣西省~`的~`東南部~、`香~`港~、`澳門~`一帶~，`海外~`華僑~`使用~`粵語~`的~`人~`也~`很~`多~。"}],"p":"yuè yǔ"}],"t":"`粵~`語~","translation":{"Deutsch":["Kantonesisch, kantonesische Sprache (S, Sprachw)","Yue (chinesiche Sprachgruppe in Südchina, Guangdong, Kanton) (S, Sprachw)"],"English":["Cantonese language"],"francais":["cantonais (langue)"]}}