{"Deutsch":"gewaltig, ausgedehnt ","English":"cord for hat","c":10,"francais":"cordon","h":[{"=":"2989","b":"ㄏㄨㄥˊ","d":[{"f":"`古代~`繫~`在~`冠冕~`下的~`帽~`帶~。","q":["《`禮記~．`雜記~`下~》：「`管仲~`鏤~`簋~`而~`朱~`紘~，`旅~`樹~`而~`反坫~，`山~`節~`而~`藻梲~，`賢~`大夫~`也~。」","`唐~．`韓愈~、`孟郊~〈`城~`南~`聯句~〉：「`朝~`冠~`飄~`彩~`紘~，`爵~`勛~`逮~`僮~`隸~。」"],"type":"`名~"},{"f":"`繩子~、`繩~`網~。","q":["《`儀禮~．`大~`射~`儀~》：「`簜~`在~`建~`鼓~`之~`間~，`鞀~`倚~`于~`頌~`磬~`西~`紘~。」","《`文選~．`班固~．`西都賦~》：「`罘網~`連~`紘~，`籠~`山~`絡~`野~。」"],"type":"`名~"},{"f":"`綱紀~、`綱維~。","q":["`漢~．`蔡邕~〈`釋~`誨~〉：「`天網~`縱~，`人~`紘~`弛~。」"],"type":"`名~"},{"f":"`宏大~、`廣大~。","q":["《`淮南子~．`精神~》：「`夫~`天地~`之~`道~，`至~`紘~`以~`大~。」"],"type":"`形~"}],"p":"hóng"}],"n":4,"r":"`糸~","t":"紘","translation":{"Deutsch":["gewaltig, ausgedehnt "],"English":["cord for hat","vast"],"francais":["cordon","vaste","expansif"]}}