{"Deutsch":"nicht vereinfachte Schreibform, traditionelles Chinesisch","English":"traditional form of Chinese, as opposed to simplified form `簡~`體~|简`体~[jian3 ti3]","francais":"Sinogramme traditionnel","h":[{"b":"ㄈㄢˊ　ㄊㄧˇ","d":[{"f":"`繁體字~`的~`簡稱~。`參見~「`繁體字~」`條~。"}],"p":"fán tǐ"}],"t":"`繁~`體~","translation":{"Deutsch":["nicht vereinfachte Schreibform, traditionelles Chinesisch"],"English":["traditional form of Chinese, as opposed to simplified form `簡~`體~|简`体~[jian3 ti3]"],"francais":["Sinogramme traditionnel"]}}