{"Deutsch":"biegsam, gefügig ","English":"archaic variant of `軟~|软[ruan3]","c":9,"h":[{"b":"ㄖㄨㄢˇ","d":[{"f":"`柔弱~、`柔軟~。","l":["`通~「`軟~」。"],"q":["《`漢書~．`卷~`六~`二~．`司馬遷~`傳~》：「`僕~`雖~`怯~`耎~`欲~`苟活~，`亦~`頗~`識~`去就之分~`矣~。」","`唐~．`李賀~〈`南~`園~〉`詩~`一~`三~`首~`之~`九~：「`泉~`沙~`耎~`臥~`鴛鴦~`暖~，`曲~`岸~`迴~`篙~`舴艋~`遲~。」"],"type":"`形~"},{"f":"`退縮~。","q":["《`史記~．`卷~`二~`七~．`天官書~》：「`其~`已~`出~`三~`日~`而~`復~，`有~`微~`入~，`入~`三~`日~`乃~`復~`盛~`出~，`是~`謂~`耎~。」","`裴駰~`集~`解~`引~`晉~`灼~`曰~：「`耎~，`退~`之~`不~`進~。」"],"type":"`動~"}],"p":"ruǎn"}],"n":3,"r":"`而~","t":"耎","translation":{"Deutsch":["biegsam, gefügig "],"English":["archaic variant of `軟~|软[ruan3]"]}}