{"Deutsch":"Heiliges Wasser  (S)","English":"holy water","francais":"eau bénite","h":[{"b":"ㄕㄥˋ　ㄕㄨㄟˇ","d":[{"f":"`信徒~`向~`神明~`禱告~`乞~`得以~`為~`可以~`驅邪~、`療~`疾~`的~`神水~。","q":["《`元史~．`卷~`一~`九~`七~．`孝友~`傳~`一~．`趙~`榮~`傳~》：「`復~`負~`母~`登~`太白~`山~，`禱~`于~`神~，`得~`聖水~`飲~`之~，`乃~`痊~。」"]},{"f":"`河川~`名~。`即今~`河北省~`房山~`縣~`的~`琉璃~`河~。","q":["`北魏~．`酈道元~《`水經注~．`聖水~`注~》：「`聖水~`自~`涿~`縣~`東~`與~`桃~`水~`合~，`水~`首~`受~`淶~`水~`于徐~`城~`東南~。」"]}],"p":"shèng shuǐ"}],"t":"`聖~`水~","translation":{"Deutsch":["Heiliges Wasser  (S)"],"English":["holy water"],"francais":["eau bénite"]}}