{"English":"son of grandfather's sister","francais":"fils de la soeur du grand-père","h":[{"b":"ㄅㄧㄠˇ　ㄕㄨˊ","d":[{"f":"`稱謂~。`用~`以~`稱~`父親~`的~`表弟~。","q":["《`文明~`小史~．`第~`二~`七~`回~》：「`少停~，`房門~`裡~`簾子~`一~`掀~，`一個~`老媽~`領~`了~`一個~`五~`六~`歲~`的~`孩子~`出來~，`向~`濟~`川~`瞌~`頭~，`叫~`表叔~。」"]}],"p":"biǎo shú"}],"t":"`表~`叔~","translation":{"English":["son of grandfather's sister","son of grandmother's brother or sister","father's younger male cousin","(Hong Kong slang) mainlander"],"francais":["fils de la soeur du grand-père","fils du frère ou la soeur de la grand-mère"]}}